{"status":"1","message":"成功","resultbody":{"searchType":2,"engineKeywordType":0,"requestId":"e63cdc1f7d86113e02a5c0762d22acc8","job":{"items":[{"property":"{\"isInitiative\":\"是\",\"pageCode\":\"sou|sou|soulb\",\"shortPageCode\":\"sou|sou|soulb\",\"searchType\":\"手动搜索职位\",\"jobRank\":\"200\",\"policyId\":\"{\\\"layer_rank_v23\\\":\\\"2099_2\\\"}\",\"keyword\":\"\",\"pageNum\":\"11\",\"requestId\":\"e63cdc1f7d86113e02a5c0762d22acc8\",\"jobType\":\"0\"}","jobId":"148965497","jobType":"0","jobName":"人力资源专员（人事运营方向）","jobTags":["3-4年","本科","五险一金","交通补贴","餐饮补贴","通讯补贴","带薪年假","岗位晋升","500强","发展空间大"],"jobNumString":"","workAreaCode":"021100","jobAreaCode":"020000","jobAreaString":"上海·闵行区","hrefAreaPinYin":"shanghai-mhq","jobAreaLevelDetail":{"provinceCode":"020000","provinceString":"上海","cityCode":"020000","cityString":"上海","districtString":"闵行区","landMarkString":""},"provideSalaryString":"9千-1.1万·14薪","issueDateString":"2024-04-16 09:48:48","confirmDateString":"2024-04-16 09:48:48","workYear":"5","workYearString":"3-4年","degreeString":"本科","industryType1":"26","industryType2":"26","industryType1Str":"房地产","industryType2Str":"房地产","funcType1Code":"0604","funcType2Code":"","major1Str":"","major2Str":"","encCoId":"B2VWMlE2U24BbQRiUj4","companyName":"万科（上海）商用置业","fullCompanyName":"万科（上海）商用置业有限公司","companyLogo":"https://img01.51jobcdn.com/fansImg/CompLogo/5/4044/4043959/4043959_120.gif?636074723839667453","companyTypeString":"已上市","companySizeString":"150-500人","companySizeCode":"3","companyIndustryType1Str":"房地产","companyIndustryType2Str":"房地产","hrUid":"3388896","hrName":"wytz559","smallHrLogoUrl":"http://img01.51jobcdn.com/imehire/userportrait/default/li_portrait_female_006_small.png","hrPosition":"人事招聘","hrMedalTitle":"","hrMedalLevel":"","showHrMedalTitle":true,"hrIsOnline":false,"isOnline":false,"hrLabels":[],"updateDateTime":"2024-04-23 16:48:21","lon":"121.361284","lat":"31.166194","isCommunicate":false,"isFromXyx":false,"isIntern":false,"isModelEmployer":false,"isQuickFeedback":true,"isPromotion":false,"isApply":false,"isExpire":false,"jobHref":"https://jobs.51job.com/shanghai-mhq/148965497.html?s=sou_sou_soulb&t=0_0&req=e63cdc1f7d86113e02a5c0762d22acc8","jobDescribe":"职责描述：\r\n一、入转调离等标准化的工作，包含劳动合同签订/续签、人事事件手续、文档管理、员工档案管理、事件信息收集、背景调查、审批流程发起和跟进、现场手续办理、合同签订/续签、文档/档案管理、转正、调动办理\r\n二、五险一金投保和工伤申报，五险一金增减保、五险一金基数调整、工伤、生育、失业申报，退休办理\r\n三、商业保险投保和理赔，投保信息收集、商业保险增减保、理赔跟进\r\n四、基础的人事服务工作，包含证明开具、***迁移、证明开具（不包含收入证明）、考勤管理（含休假额度管理）、员工数据维护和E-HR系统报表管理，输出人事月报、给业务部门提供社保证明等、合作方入离场管理、员工账号及群组管理等\r\n任职要求：\r\n1、统招本科及以上学历\r\n2、年龄24-28岁\r\n3、3年以上人事运营工作经验\r\n4、工作细致、责任心强、具有独立思考及完成工作的能力\r\n5、熟练使用EXCEL中人力系统常用函数","companyHref":"https://jobs.51job.com/all/coB2VWMlE2U24BbQRiUj4.html","allowChatOnline":false,"ctmId":2936939,"term":"0","termStr":"全职","landmarkId":"","landmarkString":"","retrieverName":"JobTermBasedRetriever","exrInfo02":"{\"retrieverName\":\"JobTermBasedRetriever\",\"referJobId\":\"\",\"intentions\":\"\",\"adExtendFunc\":\"\",\"adExtendCity\":\"\"}","hrInfoType":0,"isRemoteWork":false,"contactAllowed":"0","contactDay":"","contactTime":"","hasHrMobile":true,"jobTagsForOrder":["3-4年","本科","五险一金","交通补贴","餐饮补贴","通讯补贴","带薪年假","岗位晋升","500强","发展空间大"],"isAllowChat":true,"sesameLabelList":[{"labelName":"国有企业","labelCode":"state_owned_business","labelDefinition":"该企业为实际控制人为国务院、各地区国有资产监督管理委员会、地方人民政府或机关单位。"},{"labelName":"经营年限全国同行前20%","labelCode":"top_nationwide","labelDefinition":"据工商登记信息显示，该企业相比其他同行业更早进入市场。"},{"labelName":"大学生就业贡献","labelCode":"college_employment_contribution","labelDefinition":"据公开网络招聘信息显示，该企业在近1年内有发布过大学生就业岗位，助力大学生就业。"}],"jobWelfareCodeDataList":[{"code":"100234","chineseTitle":"五险一金","englishTitle":"","typeCode":"10035","typeTitle":"福利待遇"},{"code":"100829","chineseTitle":"交通补贴","englishTitle":"","typeCode":"10035","typeTitle":"福利待遇"},{"code":"100830","chineseTitle":"餐饮补贴","englishTitle":"","typeCode":"10035","typeTitle":"福利待遇"},{"code":"100831","chineseTitle":"通讯补贴","englishTitle":"","typeCode":"10035","typeTitle":"福利待遇"},{"code":"100843","chineseTitle":"带薪年假","englishTitle":"","typeCode":"10035","typeTitle":"福利待遇"},{"code":"100824","chineseTitle":"岗位晋升","englishTitle":"","typeCode":"10035","typeTitle":"福利待遇"}],"jobSalaryMax":"11000","jobSalaryMin":"9000","jobScheme":"qiancheng://home/show_job_info?jobid=148965497&property=%7B%22isInitiative%22%3A%22%E6%98%AF%22%2C%22pageCode%22%3A%22sou%7Csou%7Csoulb%22%2C%22shortPageCode%22%3A%22sou%7Csou%7Csoulb%22%2C%22searchType%22%3A%22%E6%89%8B%E5%8A%A8%E6%90%9C%E7%B4%A2%E8%81%8C%E4%BD%8D%22%2C%22jobRank%22%3A%22200%22%2C%22policyId%22%3A%22%7B%5C%22layer_rank_v23%5C%22%3A%5C%222099_2%5C%22%7D%22%2C%22keyword%22%3A%22%22%2C%22pageNum%22%3A%2211%22%2C%22requestId%22%3A%22e63cdc1f7d86113e02a5c0762d22acc8%22%2C%22jobType%22%3A%220%22%7D","coId":"4043959"},{"property":"{\"isInitiative\":\"是\",\"pageCode\":\"sou|sou|soulb\",\"shortPageCode\":\"sou|sou|soulb\",\"searchType\":\"手动搜索职位\",\"jobRank\":\"201\",\"policyId\":\"{\\\"layer_rank_v23\\\":\\\"2099_2\\\"}\",\"keyword\":\"\",\"pageNum\":\"11\",\"requestId\":\"e63cdc1f7d86113e02a5c0762d22acc8\",\"jobType\":\"0\"}","jobId":"154109846","jobType":"0","jobName":"人力资源专员 (MJ000421)","jobTags":["3年及以上","本科","五险一金","员工旅游","年终奖金","定期体检"],"jobNumString":"","workAreaCode":"021000","jobAreaCode":"020000","jobAreaString":"上海·浦东新区","hrefAreaPinYin":"shanghai-pdxq","jobAreaLevelDetail":{"provinceCode":"020000","provinceString":"上海","cityCode":"020000","cityString":"上海","districtString":"浦东新区","landMarkString":"张江"},"provideSalaryString":"1-2万·13薪","issueDateString":"2024-04-17 09:54:27","confirmDateString":"2024-03-29 14:33:56","workYear":"5","workYearString":"3年及以上","degreeString":"本科","industryType1":"02","industryType2":"22","industryType1Str":"电子技术/半导体/集成电路","industryType2Str":"批发/零售","funcType1Code":"0604","funcType2Code":"","major1Str":"","major2Str":"","encCoId":"VjEGYFI4BTsFZwVhUDM","companyName":"瑞芯微电子","fullCompanyName":"瑞芯微电子股份有限公司","companyLogo":"https://img01.51jobcdn.com/fansImg/CompLogo/2/1291/1290776/1290776_300.png?637235176253118983","companyTypeString":"民营","companySizeString":"500-1000人","companySizeCode":"4","companyIndustryType1Str":"电子技术/半导体/集成电路","companyIndustryType2Str":"批发/零售","hrUid":"1972706","hrName":"alice","smallHrLogoUrl":"http://img01.51jobcdn.com/imehire/userportrait/default/li_portrait_female_003_small.png","hrPosition":"HR","hrMedalTitle":"","hrMedalLevel":"","showHrMedalTitle":true,"hrIsOnline":false,"isOnline":false,"hrLabels":[],"updateDateTime":"2024-04-22 12:55:52","lon":"121.640018","lat":"31.201780","isCommunicate":false,"isFromXyx":false,"isIntern":false,"isModelEmployer":true,"isQuickFeedback":false,"isPromotion":false,"isApply":false,"isExpire":false,"jobHref":"https://jobs.51job.com/shanghai-pdxq/154109846.html?s=sou_sou_soulb&t=0_0&req=e63cdc1f7d86113e02a5c0762d22acc8","jobDescribe":"岗位职责：\r\n1、负责完成部分人才招聘工作;\r\n2、负责员工入职、离职管理及办理各类人事相关手续。\r\n3、负责劳动合同、人事档案、花名册等基础信息的建设和管理工作，确保人事信息的准确性和完整性；\r\n4、负责员工居住证积分、***、签证的办理；\r\n5、负责企业文化活动策划、宣传和执行及员工福利发放工作;\r\n6、负责考勤管理工作，协助做好员工培训工作;\r\n7、完成上级领导交办的其它工作。\r\n岗位要求：\r\n1、3年及以上半导体行业相关工作经验；\r\n2、优秀的团队协作及沟通协调能力；\r\n3、严谨的工作的态度，高效的执行力，较强的学习能力。","companyHref":"https://jobs.51job.com/all/coVjEGYFI4BTsFZwVhUDM.html","allowChatOnline":false,"ctmId":655735,"term":"0","termStr":"全职","landmarkId":"67","landmarkString":"张江","retrieverName":"JobTermBasedRetriever","exrInfo02":"{\"retrieverName\":\"JobTermBasedRetriever\",\"referJobId\":\"\",\"intentions\":\"\",\"adExtendFunc\":\"\",\"adExtendCity\":\"\"}","hrInfoType":0,"isRemoteWork":false,"contactAllowed":"0","contactDay":"","contactTime":"","hasHrMobile":true,"jobTagsForOrder":["3年及以上","本科","五险一金","员工旅游","年终奖金","定期体检"],"isAllowChat":true,"sesameLabelList":[{"labelName":"A股上市","labelCode":"listed_enterprise","labelDefinition":"该企业在中国证券交易所公开发行企业股票。"},{"labelName":"高新技术企业","labelCode":"high_new_tech_corp","labelDefinition":"发布时间:2023-12-28,评定有效期:3年,颁发机构:全国高新技术企业认定管理工作领导小组办公室。符合《高新技术企业认定管理办法》规定，符合国家重点支持的高新技术领域，持续进行研究开发与技术成果转化，形成企业核心自主知识产权，并以此为基础开展经营活动，在中国境内（不包括港、澳、台地区）注册成立一年以上的居民企业。"},{"labelName":"小巨人企业","labelCode":"little_giant_corp","labelDefinition":"评定有效期:3年。企业符合《优质中小企业梯度培育管理暂行办法》中专精特新“小巨人”企业的认定条件，是“专精特新”中小企业中的佼佼者，在中华人民共和国境内工商注册登记、连续经营3年以上，专注于细分市场、创新能力强、市场占有率高、掌握关键核心技术、质量效益优的排头兵企业。"}],"jobWelfareCodeDataList":[],"jobSalaryMax":"20000","jobSalaryMin":"10000","jobScheme":"qiancheng://home/show_job_info?jobid=154109846&property=%7B%22isInitiative%22%3A%22%E6%98%AF%22%2C%22pageCode%22%3A%22sou%7Csou%7Csoulb%22%2C%22shortPageCode%22%3A%22sou%7Csou%7Csoulb%22%2C%22searchType%22%3A%22%E6%89%8B%E5%8A%A8%E6%90%9C%E7%B4%A2%E8%81%8C%E4%BD%8D%22%2C%22jobRank%22%3A%22201%22%2C%22policyId%22%3A%22%7B%5C%22layer_rank_v23%5C%22%3A%5C%222099_2%5C%22%7D%22%2C%22keyword%22%3A%22%22%2C%22pageNum%22%3A%2211%22%2C%22requestId%22%3A%22e63cdc1f7d86113e02a5c0762d22acc8%22%2C%22jobType%22%3A%220%22%7D","coId":"1290776"},{"property":"{\"isInitiative\":\"是\",\"pageCode\":\"sou|sou|soulb\",\"shortPageCode\":\"sou|sou|soulb\",\"searchType\":\"手动搜索职位\",\"jobRank\":\"202\",\"policyId\":\"{\\\"layer_rank_v23\\\":\\\"2099_2\\\"}\",\"keyword\":\"\",\"pageNum\":\"11\",\"requestId\":\"e63cdc1f7d86113e02a5c0762d22acc8\",\"jobType\":\"0\"}","jobId":"153028171","jobType":"0","jobName":"人事管培生","jobTags":["无需经验","本科","五险一金","员工旅游","餐饮补贴","通讯补贴","专业培训","年终奖金"],"jobNumString":"","workAreaCode":"021100","jobAreaCode":"020000","jobAreaString":"上海·闵行区","hrefAreaPinYin":"shanghai-mhq","jobAreaLevelDetail":{"provinceCode":"020000","provinceString":"上海","cityCode":"020000","cityString":"上海","districtString":"闵行区","landMarkString":""},"provideSalaryString":"8千-1万","issueDateString":"2024-04-16 09:27:05","confirmDateString":"2024-04-08 15:18:55","workYear":"10","workYearString":"无需经验","degreeString":"本科","industryType1":"19","industryType2":"56","industryType1Str":"石油/化工/矿产/地质","industryType2Str":"原材料和加工","funcType1Code":"0604","funcType2Code":"","major1Str":"","major2Str":"","encCoId":"B2MGYQBhBzsAbFA3XTs","companyName":"上海保立佳化工","fullCompanyName":"上海保立佳化工股份有限公司","companyLogo":"https://img01.51jobcdn.com/fansImg/CompLogo/3/2323/2322943/2322943_120.gif?636446975581339105","companyTypeString":"已上市","companySizeString":"500-1000人","companySizeCode":"4","companyIndustryType1Str":"石油/化工/矿产/地质","companyIndustryType2Str":"原材料和加工","hrUid":"17381640","hrName":"BLJ","smallHrLogoUrl":"http://img01.51jobcdn.com/imehire/userportrait/default/li_portrait_female_001_small.png","hrPosition":"HR","hrMedalTitle":"","hrMedalLevel":"","showHrMedalTitle":true,"hrIsOnline":false,"isOnline":false,"hrLabels":["今日活跃"],"updateDateTime":"2024-04-29 11:38:58","lon":"121.405503","lat":"31.050585","isCommunicate":false,"isFromXyx":false,"isIntern":false,"isModelEmployer":false,"isQuickFeedback":true,"isPromotion":false,"isApply":false,"isExpire":false,"jobHref":"https://jobs.51job.com/shanghai-mhq/153028171.html?s=sou_sou_soulb&t=0_0&req=e63cdc1f7d86113e02a5c0762d22acc8","jobDescribe":"岗位职责：\n1、负责业务部门整体人力资源支持工作，对工作结果负责；\n2、掌握所辖部门的业务和团队状况，促进公司整体人力资源战略的有效实施和业务发展战略的达成；\n3、协助进行内部组织优化，人才配置优化，保障骨干员工稳定；\n\n任职资格：\n1、本科及以上学历，人力资源相关专业毕业。\n2、具有极强的责任心，较强的计划性和实施执行能力，以及解决复杂问题的能力。\n\n本岗位针对应届毕业生，欢迎应届生投递。","companyHref":"https://jobs.51job.com/all/coB2MGYQBhBzsAbFA3XTs.html","allowChatOnline":false,"ctmId":1268612,"term":"0","termStr":"全职","landmarkId":"","landmarkString":"","retrieverName":"JobTermBasedRetriever","exrInfo02":"{\"retrieverName\":\"JobTermBasedRetriever\",\"referJobId\":\"\",\"intentions\":\"\",\"adExtendFunc\":\"\",\"adExtendCity\":\"\"}","hrInfoType":0,"isRemoteWork":false,"contactAllowed":"0","contactDay":"","contactTime":"","hasHrMobile":true,"jobTagsForOrder":["无需经验","本科","五险一金","员工旅游","餐饮补贴","通讯补贴","专业培训","年终奖金"],"isAllowChat":true,"sesameLabelList":[{"labelName":"A股上市","labelCode":"listed_enterprise","labelDefinition":"该企业在中国证券交易所公开发行企业股票。"},{"labelName":"A级纳税人","labelCode":"a_taxpayer","labelDefinition":"评定年份:2022。税务部门采用年度评价指标得分和直接判级相结合的方式，依据纳税人信用历史信息、税务内部信息和外部信息等内容对纳税人进行信用评价，按照信用程度设为A、B、C、D四级，A级纳税人是税务部门评定的纳税信用级别最高的纳税人。"},{"labelName":"全国多家直营店","labelCode":"national_multistore","labelDefinition":"企业在全国拥有多家连锁直营店铺。"}],"jobWelfareCodeDataList":[{"code":"100234","chineseTitle":"五险一金","englishTitle":"","typeCode":"10035","typeTitle":"福利待遇"},{"code":"100828","chineseTitle":"员工旅游","englishTitle":"","typeCode":"10035","typeTitle":"福利待遇"},{"code":"100830","chineseTitle":"餐饮补贴","englishTitle":"","typeCode":"10035","typeTitle":"福利待遇"},{"code":"100831","chineseTitle":"通讯补贴","englishTitle":"","typeCode":"10035","typeTitle":"福利待遇"},{"code":"100832","chineseTitle":"专业培训","englishTitle":"","typeCode":"10035","typeTitle":"福利待遇"},{"code":"100835","chineseTitle":"年终奖金","englishTitle":"","typeCode":"10035","typeTitle":"福利待遇"}],"jobSalaryMax":"10000","jobSalaryMin":"8000","jobScheme":"qiancheng://home/show_job_info?jobid=153028171&property=%7B%22isInitiative%22%3A%22%E6%98%AF%22%2C%22pageCode%22%3A%22sou%7Csou%7Csoulb%22%2C%22shortPageCode%22%3A%22sou%7Csou%7Csoulb%22%2C%22searchType%22%3A%22%E6%89%8B%E5%8A%A8%E6%90%9C%E7%B4%A2%E8%81%8C%E4%BD%8D%22%2C%22jobRank%22%3A%22202%22%2C%22policyId%22%3A%22%7B%5C%22layer_rank_v23%5C%22%3A%5C%222099_2%5C%22%7D%22%2C%22keyword%22%3A%22%22%2C%22pageNum%22%3A%2211%22%2C%22requestId%22%3A%22e63cdc1f7d86113e02a5c0762d22acc8%22%2C%22jobType%22%3A%220%22%7D","coId":"2322943"},{"property":"{\"isInitiative\":\"是\",\"pageCode\":\"sou|sou|soulb\",\"shortPageCode\":\"sou|sou|soulb\",\"searchType\":\"手动搜索职位\",\"jobRank\":\"203\",\"policyId\":\"{\\\"layer_rank_v23\\\":\\\"2099_2\\\"}\",\"keyword\":\"\",\"pageNum\":\"11\",\"requestId\":\"e63cdc1f7d86113e02a5c0762d22acc8\",\"jobType\":\"0\"}","jobId":"154387075","jobType":"0","jobName":"2024年校招——人力","jobTags":["无需经验","本科","五险一金","补充医疗保险","免费班车","专业培训","年终奖金","绩效奖金","定期体检"],"jobNumString":"","workAreaCode":"021500","jobAreaCode":"020000","jobAreaString":"上海·松江区","hrefAreaPinYin":"shanghai-sjq","jobAreaLevelDetail":{"provinceCode":"020000","provinceString":"上海","cityCode":"020000","cityString":"上海","districtString":"松江区","landMarkString":""},"provideSalaryString":"6-8.5千·13薪","issueDateString":"2024-04-15 18:40:55","confirmDateString":"2024-04-15 18:40:55","workYear":"10","workYearString":"无需经验","degreeString":"本科","industryType1":"46","industryType2":"","industryType1Str":"医疗/护理/卫生","industryType2Str":"","funcType1Code":"0604","funcType2Code":"","major1Str":"心理学","major2Str":"人力资源管理","encCoId":"UTQBZ1U1BDoOagxvUTU","companyName":"泰康健康产业投资控股","fullCompanyName":"泰康健康产业投资控股有限公司","companyLogo":"https://img01.51jobcdn.com/fansImg/CompLogo/4/3231/3230101/4567706038478190247_300.png?1660201738682","companyTypeString":"民营","companySizeString":"10000人以上","companySizeCode":"7","companyIndustryType1Str":"医疗/护理/卫生","hrUid":"5168301","hrName":"石女士","smallHrLogoUrl":"http://img01.51jobcdn.com/imehire/userportrait/default/li_portrait_female_004_small.png","hrPosition":"人力资源专员","hrMedalTitle":"","hrMedalLevel":"","showHrMedalTitle":true,"hrIsOnline":false,"isOnline":false,"hrLabels":["简历处理快"],"updateDateTime":"2024-04-15 18:42:55","lon":"121.222466","lat":"31.075365","isCommunicate":false,"isFromXyx":false,"isIntern":false,"isModelEmployer":false,"isQuickFeedback":false,"isPromotion":false,"isApply":false,"isExpire":false,"jobHref":"https://jobs.51job.com/shanghai-sjq/154387075.html?s=sou_sou_soulb&t=0_0&req=e63cdc1f7d86113e02a5c0762d22acc8","jobDescribe":"1、参与招聘工作；\n2、协助实施员工发展计划和人才梯队建设；\n3、协助进行薪酬、绩效管理，落实激励考核机制；\n4、协助组织开展各类培训，实施员工关怀计划、荣誉体系等\n\n1、本科及以上学历，人力资源管理、心理学相关专业；\n2、具有较强的沟通协调能力和团队合作意识；\n3、熟练应用办公软件和数据统计工具。","companyHref":"https://jobs.51job.com/all/coUTQBZ1U1BDoOagxvUTU.html","allowChatOnline":false,"ctmId":2130944,"term":"0","termStr":"全职","landmarkId":"","landmarkString":"","retrieverName":"JobTermBasedRetriever","exrInfo02":"{\"retrieverName\":\"JobTermBasedRetriever\",\"referJobId\":\"\",\"intentions\":\"\",\"adExtendFunc\":\"\",\"adExtendCity\":\"\"}","hrInfoType":0,"isRemoteWork":false,"contactAllowed":"0","contactDay":"","contactTime":"","hasHrMobile":true,"jobTagsForOrder":["无需经验","本科","五险一金","补充医疗保险","免费班车","专业培训","年终奖金","绩效奖金","定期体检"],"isAllowChat":true,"sesameLabelList":[{"labelName":"绝对控股10家公司","labelCode":"absolute_holding_companies","labelDefinition":"该企业绝对控股10公司，绝对控股是指出资额占有限责任公司资本总额百分之六十七以上或者其持有的股份占股份有限公司股本总额百分之六十七以上。"},{"labelName":"战略性新兴领域创新能力","labelCode":"new_strategic_industry","labelDefinition":"该企业申请、授权的专利属于以重大技术突破和重大发展需求为基础，对经济社会全局和长远发展具有重大引领带动作用，知识技术密集、物质资源消耗少、成长潜力大、综合效益好的战略性新兴产业。"},{"labelName":"拥有节能环保技术","labelCode":"environmental_protection","labelDefinition":"该企业申请、授权的专利领域属于节约能源资源、发展循环经济、保护生态环境提供物质基础和技术保障的节能环保绿色产业。"}],"jobWelfareCodeDataList":[{"code":"100234","chineseTitle":"五险一金","englishTitle":"","typeCode":"10035","typeTitle":"福利待遇"},{"code":"100825","chineseTitle":"补充医疗保险","englishTitle":"","typeCode":"10035","typeTitle":"福利待遇"},{"code":"100827","chineseTitle":"免费班车","englishTitle":"","typeCode":"10035","typeTitle":"福利待遇"},{"code":"100832","chineseTitle":"专业培训","englishTitle":"","typeCode":"10035","typeTitle":"福利待遇"},{"code":"100835","chineseTitle":"年终奖金","englishTitle":"","typeCode":"10035","typeTitle":"福利待遇"},{"code":"100834","chineseTitle":"绩效奖金","englishTitle":"","typeCode":"10035","typeTitle":"福利待遇"},{"code":"100838","chineseTitle":"定期体检","englishTitle":"","typeCode":"10035","typeTitle":"福利待遇"}],"jobSalaryMax":"8500","jobSalaryMin":"6000","jobScheme":"qiancheng://home/show_job_info?jobid=154387075&property=%7B%22isInitiative%22%3A%22%E6%98%AF%22%2C%22pageCode%22%3A%22sou%7Csou%7Csoulb%22%2C%22shortPageCode%22%3A%22sou%7Csou%7Csoulb%22%2C%22searchType%22%3A%22%E6%89%8B%E5%8A%A8%E6%90%9C%E7%B4%A2%E8%81%8C%E4%BD%8D%22%2C%22jobRank%22%3A%22203%22%2C%22policyId%22%3A%22%7B%5C%22layer_rank_v23%5C%22%3A%5C%222099_2%5C%22%7D%22%2C%22keyword%22%3A%22%22%2C%22pageNum%22%3A%2211%22%2C%22requestId%22%3A%22e63cdc1f7d86113e02a5c0762d22acc8%22%2C%22jobType%22%3A%220%22%7D","coId":"3230101"},{"property":"{\"isInitiative\":\"是\",\"pageCode\":\"sou|sou|soulb\",\"shortPageCode\":\"sou|sou|soulb\",\"searchType\":\"手动搜索职位\",\"jobRank\":\"204\",\"policyId\":\"{\\\"layer_rank_v23\\\":\\\"2099_2\\\"}\",\"keyword\":\"\",\"pageNum\":\"11\",\"requestId\":\"e63cdc1f7d86113e02a5c0762d22acc8\",\"jobType\":\"0\"}","jobId":"144003332","jobType":"0","jobName":"人力资源专员","jobTags":["2年","本科","招聘","培训","考勤","员工关系","薪酬绩效","人力资源","人事","人事专员","人事主管","人力资源主管","周末双休","餐饮补贴","免费班车","定期体检","绩效奖金","五险二金"],"jobNumString":"","workAreaCode":"021000","jobAreaCode":"020000","jobAreaString":"上海·浦东新区","hrefAreaPinYin":"shanghai-pdxq","jobAreaLevelDetail":{"provinceCode":"020000","provinceString":"上海","cityCode":"020000","cityString":"上海","districtString":"浦东新区","landMarkString":"临港新城"},"provideSalaryString":"8千-1.5万·13薪","issueDateString":"2024-04-29 11:01:59","confirmDateString":"2024-03-22 08:32:46","workYear":"4","workYearString":"2年","degreeString":"本科","industryType1":"55","industryType2":"55","industryType1Str":"航天/航空","industryType2Str":"航天/航空","funcType1Code":"0604","funcType2Code":"","major1Str":"","major2Str":"","encCoId":"B2NQMF80DjRVMQ1uVjY","companyName":"上海格思信息技术","fullCompanyName":"上海格思信息技术有限公司","companyLogo":"https://img01.51jobcdn.com/fansImg/CompLogo/3/2485/2484105/207284608437575932079_300.png?1676362186034","companyTypeString":"国企","companySizeString":"150-500人","companySizeCode":"3","companyIndustryType1Str":"航天/航空","companyIndustryType2Str":"航天/航空","hrUid":"1697055","hrName":"魏女士","smallHrLogoUrl":"http://img01.51jobcdn.com/imehire/userportrait/default/li_portrait_la_10_small.png","hrPosition":"招聘主管","hrMedalTitle":"","hrMedalLevel":"","showHrMedalTitle":true,"hrIsOnline":false,"isOnline":false,"hrLabels":["简历处理快"],"updateDateTime":"2024-04-11 17:52:16","lon":"121.918671","lat":"30.952154","isCommunicate":false,"isFromXyx":false,"isIntern":false,"isModelEmployer":false,"isQuickFeedback":true,"isPromotion":false,"isApply":false,"isExpire":false,"jobHref":"https://jobs.51job.com/shanghai-pdxq/144003332.html?s=sou_sou_soulb&t=0_0&req=e63cdc1f7d86113e02a5c0762d22acc8","jobDescribe":"【岗位职责】\n1、组织编制公司年度招聘计划并执行，筛选简历、预约候选人，组织人员招聘面试工作；\n2、组织编制公司年度培训计划并执行，完成培训记录及有效性评价，保障相关岗位持证上岗；\n3、负责人员招退工、社保新增、转入转出，落户人员社保属性变更等工作；\n4、负责员工劳动合同、保密协议的签订、续签、变更与终止；\n5、负责员工入、离、转、升等手续的办理；\n6、负责员工居住证积分及落户办理；\n7、负责员工考勤、档案等管理工作；\n8、 领导交办的其他事项。\n【任职资格】\n1、大学本科及以上学历，人力资源管理专业优先考虑；\n2、两年人力资源工作经验及以上；\n3、熟练使用Office办公软件，excel、PPT精通者优先考虑；\n4、能吃苦，工作效率高；\n5、做事细致、认真、有耐心。\n\n注：工作地在临港新片区","companyHref":"https://jobs.51job.com/all/coB2NQMF80DjRVMQ1uVjY.html","allowChatOnline":false,"ctmId":1407953,"term":"0","termStr":"全职","landmarkId":"2718","landmarkString":"临港新城","retrieverName":"JobTermBasedRetriever","exrInfo02":"{\"retrieverName\":\"JobTermBasedRetriever\",\"referJobId\":\"\",\"intentions\":\"\",\"adExtendFunc\":\"\",\"adExtendCity\":\"\"}","hrInfoType":0,"isRemoteWork":false,"contactAllowed":"","contactDay":"","contactTime":"","hasHrMobile":true,"jobTagsForOrder":["2年","本科","招聘","培训","考勤","员工关系","薪酬绩效","人力资源","人事","人事专员","人事主管","人力资源主管","周末双休","餐饮补贴","免费班车","定期体检","绩效奖金","五险二金"],"isAllowChat":true,"sesameLabelList":[{"labelName":"国有企业","labelCode":"state_owned_business","labelDefinition":"该企业为实际控制人为国务院、各地区国有资产监督管理委员会、地方人民政府或机关单位。"},{"labelName":"高新技术企业","labelCode":"high_new_tech_corp","labelDefinition":"发布时间:2023-11-15,评定有效期:3年,颁发机构:全国高新技术企业认定管理工作领导小组办公室。符合《高新技术企业认定管理办法》规定，符合国家重点支持的高新技术领域，持续进行研究开发与技术成果转化，形成企业核心自主知识产权，并以此为基础开展经营活动，在中国境内（不包括港、澳、台地区）注册成立一年以上的居民企业。"},{"labelName":"科技型中小企业","labelCode":"technical_sme","labelDefinition":"发布时间:2023-06-25,评定有效期:3年,颁发机构:科学技术部火炬高技术产业开发中心。科技型中小企业是指依托一定数量的科技人员从事科学技术研究开发活动，取得自主知识产权并将其转化为高新技术产品或服务从而实现可持续发展，在中国境内（不包括港、澳、台地区）注册的中小企业。"}],"jobWelfareCodeDataList":[{"code":"100841","chineseTitle":"周末双休","englishTitle":"","typeCode":"10035","typeTitle":"福利待遇"},{"code":"100830","chineseTitle":"餐饮补贴","englishTitle":"","typeCode":"10035","typeTitle":"福利待遇"},{"code":"100827","chineseTitle":"免费班车","englishTitle":"","typeCode":"10035","typeTitle":"福利待遇"},{"code":"100838","chineseTitle":"定期体检","englishTitle":"","typeCode":"10035","typeTitle":"福利待遇"},{"code":"100834","chineseTitle":"绩效奖金","englishTitle":"","typeCode":"10035","typeTitle":"福利待遇"}],"jobSalaryMax":"15000","jobSalaryMin":"8000","jobScheme":"qiancheng://home/show_job_info?jobid=144003332&property=%7B%22isInitiative%22%3A%22%E6%98%AF%22%2C%22pageCode%22%3A%22sou%7Csou%7Csoulb%22%2C%22shortPageCode%22%3A%22sou%7Csou%7Csoulb%22%2C%22searchType%22%3A%22%E6%89%8B%E5%8A%A8%E6%90%9C%E7%B4%A2%E8%81%8C%E4%BD%8D%22%2C%22jobRank%22%3A%22204%22%2C%22policyId%22%3A%22%7B%5C%22layer_rank_v23%5C%22%3A%5C%222099_2%5C%22%7D%22%2C%22keyword%22%3A%22%22%2C%22pageNum%22%3A%2211%22%2C%22requestId%22%3A%22e63cdc1f7d86113e02a5c0762d22acc8%22%2C%22jobType%22%3A%220%22%7D","coId":"2484105"},{"property":"{\"isInitiative\":\"是\",\"pageCode\":\"sou|sou|soulb\",\"shortPageCode\":\"sou|sou|soulb\",\"searchType\":\"手动搜索职位\",\"jobRank\":\"205\",\"policyId\":\"{\\\"layer_rank_v23\\\":\\\"2099_2\\\"}\",\"keyword\":\"\",\"pageNum\":\"11\",\"requestId\":\"e63cdc1f7d86113e02a5c0762d22acc8\",\"jobType\":\"0\"}","jobId":"154376194","jobType":"0","jobName":"行政人事专员","jobTags":["无需经验","本科","周末双休","五险一金","绩效奖金","节日福利","餐饮补贴","高温补贴","加班补贴"],"jobNumString":"","workAreaCode":"020600","jobAreaCode":"020000","jobAreaString":"上海·普陀区","hrefAreaPinYin":"shanghai-ptq","jobAreaLevelDetail":{"provinceCode":"020000","provinceString":"上海","cityCode":"020000","cityString":"上海","districtString":"普陀区","landMarkString":""},"provideSalaryString":"6-7千·14薪","issueDateString":"2024-04-15 13:35:04","confirmDateString":"2024-04-15 13:35:03","workYear":"10","workYearString":"无需经验","degreeString":"本科","industryType1":"04","industryType2":"14","industryType1Str":"贸易/进出口","industryType2Str":"机械/设备/重工","funcType1Code":"0604","funcType2Code":"","major1Str":"行政管理","major2Str":"","encCoId":"AGMAbFIxATdUMw1nBWk","companyName":"上海金田铜业","fullCompanyName":"上海金田铜业有限公司","companyLogo":"https://img04.51jobcdn.com/im/mkt/app/51job_phone/app/homelogo/new/home_logo_default_trade.png","companyTypeString":"民营","companySizeString":"150-500人","companySizeCode":"3","companyIndustryType1Str":"贸易/进出口","companyIndustryType2Str":"机械/设备/重工","hrUid":"6477392","hrName":"Kiki","smallHrLogoUrl":"http://img01.51jobcdn.com/imehire/userportrait/default/li_portrait_female_003_small.png","hrPosition":"人事负责人","hrActiveStatusGreen":"刚刚活跃","hrMedalTitle":"","hrMedalLevel":"","showHrMedalTitle":true,"hrIsOnline":false,"isOnline":false,"hrLabels":["回复率高"],"updateDateTime":"2024-04-22 14:24:32","lon":"121.429682","lat":"31.249460","isCommunicate":false,"isFromXyx":false,"isIntern":false,"isModelEmployer":false,"isQuickFeedback":true,"isPromotion":false,"isApply":false,"isExpire":false,"jobHref":"https://jobs.51job.com/shanghai-ptq/154376194.html?s=sou_sou_soulb&t=0_0&req=e63cdc1f7d86113e02a5c0762d22acc8","jobDescribe":"工作内容：\n负责公司的行政人事工作，包括员工档案管理、项目管理跟进、员工关系维护、活动组织安排等。\n主要职责：\n- 负责公司员工档案管理和维护，包括入职、调岗、离职等档案记录，以及员工信息更新；\n- 负责公司福利制定和执行，包括节假日福利、团建活动等；\n- 负责员工关系维护，包括员工生日、节日礼物等关怀活动，以及处理员工纠纷等；\n- 协助完成其他行政人事工作，如招聘预算、员工培训等。\n职位要求：\n- 优秀的应届生，本科及以上学历，具备较强的专业学习能力；\n- 熟悉行政人事工作流程，具备一定的招聘、薪酬和员工关系维护经验；\n- 良好的沟通能力和团队合作意识，具备较强的责任心和执行力；\n- 熟练使用办公软件，如Word、Excel、PowerPoint等。","companyHref":"https://jobs.51job.com/all/coAGMAbFIxATdUMw1nBWk.html","allowChatOnline":false,"ctmId":4701278,"term":"0","termStr":"全职","landmarkId":"","landmarkString":"","retrieverName":"JobTermBasedRetriever","exrInfo02":"{\"retrieverName\":\"JobTermBasedRetriever\",\"referJobId\":\"\",\"intentions\":\"\",\"adExtendFunc\":\"\",\"adExtendCity\":\"\"}","hrInfoType":0,"isRemoteWork":false,"contactAllowed":"0","contactDay":"","contactTime":"","hasHrMobile":true,"jobTagsForOrder":["无需经验","本科","周末双休","五险一金","绩效奖金","节日福利","餐饮补贴","高温补贴","加班补贴"],"isAllowChat":true,"sesameLabelList":[{"labelName":"连续6年A级纳税人","labelCode":"consec_years","labelDefinition":"税务部门采用年度评价指标得分和直接判级相结合的方式，依据纳税人信用历史信息、税务内部信息和外部信息等内容对纳税人进行信用评价，按照信用程度设为A、B、C、D四级，A级纳税人是税务部门评定的纳税信用级别最高的纳税人。"},{"labelName":"经营年限全国同行前5%","labelCode":"top_nationwide","labelDefinition":"据工商登记信息显示，该企业相比其他同行业更早进入市场。"}],"jobWelfareCodeDataList":[{"code":"100841","chineseTitle":"周末双休","englishTitle":"","typeCode":"10035","typeTitle":"福利待遇"},{"code":"100234","chineseTitle":"五险一金","englishTitle":"","typeCode":"10035","typeTitle":"福利待遇"},{"code":"100834","chineseTitle":"绩效奖金","englishTitle":"","typeCode":"10035","typeTitle":"福利待遇"},{"code":"100842","chineseTitle":"节日福利","englishTitle":"","typeCode":"10035","typeTitle":"福利待遇"},{"code":"100830","chineseTitle":"餐饮补贴","englishTitle":"","typeCode":"10035","typeTitle":"福利待遇"},{"code":"100850","chineseTitle":"高温补贴","englishTitle":"","typeCode":"10035","typeTitle":"福利待遇"},{"code":"100782","chineseTitle":"加班补贴","englishTitle":"","typeCode":"10035","typeTitle":"福利待遇"}],"jobSalaryMax":"7000","jobSalaryMin":"6000","jobScheme":"qiancheng://home/show_job_info?jobid=154376194&property=%7B%22isInitiative%22%3A%22%E6%98%AF%22%2C%22pageCode%22%3A%22sou%7Csou%7Csoulb%22%2C%22shortPageCode%22%3A%22sou%7Csou%7Csoulb%22%2C%22searchType%22%3A%22%E6%89%8B%E5%8A%A8%E6%90%9C%E7%B4%A2%E8%81%8C%E4%BD%8D%22%2C%22jobRank%22%3A%22205%22%2C%22policyId%22%3A%22%7B%5C%22layer_rank_v23%5C%22%3A%5C%222099_2%5C%22%7D%22%2C%22keyword%22%3A%22%22%2C%22pageNum%22%3A%2211%22%2C%22requestId%22%3A%22e63cdc1f7d86113e02a5c0762d22acc8%22%2C%22jobType%22%3A%220%22%7D","coId":"5808299"},{"property":"{\"isInitiative\":\"是\",\"pageCode\":\"sou|sou|soulb\",\"shortPageCode\":\"sou|sou|soulb\",\"searchType\":\"手动搜索职位\",\"jobRank\":\"206\",\"policyId\":\"{\\\"layer_rank_v23\\\":\\\"2099_2\\\"}\",\"keyword\":\"\",\"pageNum\":\"11\",\"requestId\":\"e63cdc1f7d86113e02a5c0762d22acc8\",\"jobType\":\"0\"}","jobId":"154375139","jobType":"0","jobName":"外服人事专员（杨浦，户政）","jobTags":["2年及以上","本科","户政","五险一金"],"jobNumString":"","workAreaCode":"020400","jobAreaCode":"020000","jobAreaString":"上海·长宁区","hrefAreaPinYin":"shanghai-cnq","jobAreaLevelDetail":{"provinceCode":"020000","provinceString":"上海","cityCode":"020000","cityString":"上海","districtString":"长宁区","landMarkString":""},"provideSalaryString":"8千-1万·13薪","issueDateString":"2024-04-15 13:25:59","confirmDateString":"2024-04-15 13:25:59","workYear":"4","workYearString":"2年及以上","degreeString":"本科","industryType1":"07","industryType2":"","industryType1Str":"专业服务(咨询、人力资源、财会)","industryType2Str":"","funcType1Code":"0604","funcType2Code":"","major1Str":"","major2Str":"","encCoId":"B2RQMwBiUWwAZFQw","companyName":"上海外服（集团）","fullCompanyName":"上海外服（集团）有限公司","companyLogo":"https://img01.51jobcdn.com/fansImg/CompLogo/1/572/571317/571317_300.jpg?636716707917592216","companyTypeString":"国企","companySizeString":"1000-5000人","companySizeCode":"5","companyIndustryType1Str":"专业服务(咨询、人力资源、财会)","hrUid":"17426923","hrName":"HR","smallHrLogoUrl":"http://img01.51jobcdn.com/imehire/userportrait/default/li_portrait_male_003_small.png","hrPosition":"招聘经理","hrMedalTitle":"","hrMedalLevel":"","showHrMedalTitle":true,"hrIsOnline":false,"isOnline":false,"hrLabels":["简历处理快"],"updateDateTime":"2024-04-15 13:27:59","lon":"121.431795","lat":"31.216802","isCommunicate":false,"isFromXyx":false,"isIntern":false,"isModelEmployer":false,"isQuickFeedback":false,"isPromotion":false,"isApply":false,"isExpire":false,"jobHref":"https://jobs.51job.com/shanghai-cnq/154375139.html?s=sou_sou_soulb&t=0_0&req=e63cdc1f7d86113e02a5c0762d22acc8","jobDescribe":"1)\t负责上海员工居住证积分、居转户、人才引进落户、应届生落户、留学生落户等业务办理，包括材料收取、初审、网上填报、材料递交等；\r\n2)\t线上线下解答员工、HR等的户证相关问题咨询；\r\n3)\t跟进户证申报审批进度，及时将进度、审批结果反馈员工，协助员工办理后续事宜；\r\n4)\t收集、解读相关政策变化，维护政府机构老师关系；\r\n5)\t协助中国员工、外籍员工办理签证业务；\r\n6)\t梳理、编写、更新SOP等工作资料，优化工作流程；\r\n7)\t其他SSC相关工作；\r\n岗位要求：\r\n1）\t有2年及以上户证业务办理工作经验，精通户证政策、实操流程；\r\n2）\t善于沟通、应变能力强、具有服务意识、风险管控意识；\r\n3）\t工作积极主动、认真负责；\r\n4）\t有较强的学习能力、善于思考、勇于突破；\r\n5）\t有英语读写能力；","companyHref":"https://jobs.51job.com/all/coB2RQMwBiUWwAZFQw.html","allowChatOnline":false,"ctmId":512910,"term":"0","termStr":"全职","landmarkId":"","landmarkString":"","retrieverName":"JobTermBasedRetriever","exrInfo02":"{\"retrieverName\":\"JobTermBasedRetriever\",\"referJobId\":\"\",\"intentions\":\"\",\"adExtendFunc\":\"\",\"adExtendCity\":\"\"}","hrInfoType":0,"isRemoteWork":false,"contactAllowed":"0","contactDay":"","contactTime":"","hasHrMobile":true,"jobTagsForOrder":["2年及以上","本科","户政","五险一金"],"isAllowChat":true,"sesameLabelList":[{"labelName":"国有企业","labelCode":"state_owned_business","labelDefinition":"该企业为实际控制人为国务院、各地区国有资产监督管理委员会、地方人民政府或机关单位。"},{"labelName":"上市企业子公司","labelCode":"stock_market_child","labelDefinition":"经芝麻通过公开数据识别，企业为外服控股子公司。"},{"labelName":"国企供应商","labelCode":"gov_owned_supplier","labelDefinition":"经芝麻通过公开数据识别，该企业过去1年曾中标国企单位的招标项目。属于工银安盛人寿保险有限公司、华侨城物业（集团）有限公司天津分公司、融通人力资源开发有限公司、北京华侨城物业服务有限公司供应商，其具有较高的资金实力和经营能力。"}],"jobWelfareCodeDataList":[{"code":"100234","chineseTitle":"五险一金","englishTitle":"","typeCode":"10035","typeTitle":"福利待遇"}],"jobSalaryMax":"10000","jobSalaryMin":"8000","jobScheme":"qiancheng://home/show_job_info?jobid=154375139&property=%7B%22isInitiative%22%3A%22%E6%98%AF%22%2C%22pageCode%22%3A%22sou%7Csou%7Csoulb%22%2C%22shortPageCode%22%3A%22sou%7Csou%7Csoulb%22%2C%22searchType%22%3A%22%E6%89%8B%E5%8A%A8%E6%90%9C%E7%B4%A2%E8%81%8C%E4%BD%8D%22%2C%22jobRank%22%3A%22206%22%2C%22policyId%22%3A%22%7B%5C%22layer_rank_v23%5C%22%3A%5C%222099_2%5C%22%7D%22%2C%22keyword%22%3A%22%22%2C%22pageNum%22%3A%2211%22%2C%22requestId%22%3A%22e63cdc1f7d86113e02a5c0762d22acc8%22%2C%22jobType%22%3A%220%22%7D","coId":"571317"},{"property":"{\"isInitiative\":\"是\",\"pageCode\":\"sou|sou|soulb\",\"shortPageCode\":\"sou|sou|soulb\",\"searchType\":\"手动搜索职位\",\"jobRank\":\"207\",\"policyId\":\"{\\\"layer_rank_v23\\\":\\\"2099_2\\\"}\",\"keyword\":\"\",\"pageNum\":\"11\",\"requestId\":\"e63cdc1f7d86113e02a5c0762d22acc8\",\"jobType\":\"0\"}","jobId":"151497515","jobType":"0","jobName":"高级人事专员","jobTags":["3-4年","本科","培训","办公软件","招聘","谈判","人事","网络","培训计划","法律法规","简历筛选","猎头","定期体检","员工旅游","餐饮补贴","五险一金","年终奖金","生日福利"],"jobNumString":"","workAreaCode":"020000","jobAreaCode":"020000","jobAreaString":"上海","hrefAreaPinYin":"shanghai","jobAreaLevelDetail":{"provinceCode":"020000","provinceString":"上海","cityCode":"020000","cityString":"上海","landMarkString":""},"provideSalaryString":"9千-1.3万·13薪","issueDateString":"2024-04-15 13:12:20","confirmDateString":"2024-04-15 13:12:20","workYear":"5","workYearString":"3-4年","degreeString":"本科","industryType1":"48","industryType2":"48","industryType1Str":"公关/市场推广/会展","industryType2Str":"公关/市场推广/会展","funcType1Code":"0604","funcType2Code":"","major1Str":"","major2Str":"","encCoId":"CG1RNV89AToOagdlVjU","companyName":"中贸慕尼黑展览（上海）","fullCompanyName":"中贸慕尼黑展览（上海）有限公司","companyLogo":"https://img01.51jobcdn.com/fansImg/CompLogo/4/3016/3015116/203271063759166059767_300.png?1705653774499","companyTypeString":"合资","companySizeString":"50-150人","companySizeCode":"2","companyIndustryType1Str":"公关/市场推广/会展","companyIndustryType2Str":"公关/市场推广/会展","hrUid":"19339927","hrName":"MMZM-HR","smallHrLogoUrl":"http://img01.51jobcdn.com/imehire/userportrait/default/li_portrait_female_002_small.png","hrPosition":"人事","hrMedalTitle":"","hrMedalLevel":"","showHrMedalTitle":true,"hrIsOnline":false,"isOnline":false,"hrLabels":["简历处理快"],"updateDateTime":"2024-04-15 13:12:20","lon":"121.464111","lat":"31.197554","isCommunicate":false,"isFromXyx":false,"isIntern":false,"isModelEmployer":false,"isQuickFeedback":false,"isPromotion":false,"isApply":false,"isExpire":false,"jobHref":"https://jobs.51job.com/shanghai/151497515.html?s=sou_sou_soulb&t=0_0&req=e63cdc1f7d86113e02a5c0762d22acc8","jobDescribe":"高级人事专员（Senior HR Specialist）\n岗位职责：\n1、根据公司经营规划，深入了解公司各业务部门，准确预测岗位需求，形成精准岗位说明书，通过合理渠道发布，多种渠道快速获取更多候选人，建立人才库。\n2、负责通过多种面试方式正确评估候选人能力；\n3、负责把控简历筛选、面试、笔试等环节，合理推进招聘进程，并对候选人及时反馈，最终完成公司的对人才招募、留任的结果；\n4、负责员工入职、试用期、续签、离职管理、与部门深度对接，不断优化招聘流程和员工，保证公司阶梯式人才储备。\n5、根据公司经营规划和需求，负责制定和落实公司全年的培训计划、培训课件的开发以及培训工作的实施等相关工作；\n6、负责挑选并学习外采课程，结合业务实际，提炼思路及话术，形成工具包及培训课件，包含但不限于文字，视频，音频等。\n7、根据市场和业务需求，协助各业务部门制定培训内容并进行培训，并组建、管理和考核内部培训讲师团队的工作；\n8、负责外部培训机构和讲师资源的收集、整合及管理工作；\n9、协助上级完成本部门内部培训课件，配合完成公司培训要求；\n10、完成领导交办的其他人事工作任务。\n岗位要求：\n1、本科学位及以上学历。具备连续3年以上相关人事工作经验。\n 有连续2年以上展会公司人事或企业内部培训相关工作经验优先；\n2、具有较强的组织协调能力和人际交往能力，能够有效地推动人事工作的顺利进行；\n3、具有较强的沟通能力和谈判能力，能够与候选人保持良好的沟通和谈判关系；\n4、具有较强的抗压能力和自主学习能力。\n5、熟悉招聘市场和渠道，能运用各种招聘面试技巧和方法。\n6、熟悉人力资源培训及人才发展体系，有良好的文字功底，能够独立撰写培训课件、招聘广告、等相关文件；\n8、熟练使用办公软件和设计等工具，具备基本的网络知识；\n9、熟悉人事相关法律法规政策。\n10、能够保守企业机密，并严格遵守相关法律法规。","companyHref":"https://jobs.51job.com/all/coCG1RNV89AToOagdlVjU.html","allowChatOnline":false,"ctmId":1919447,"term":"0","termStr":"全职","landmarkId":"","landmarkString":"","retrieverName":"JobTermBasedRetriever","exrInfo02":"{\"retrieverName\":\"JobTermBasedRetriever\",\"referJobId\":\"\",\"intentions\":\"\",\"adExtendFunc\":\"\",\"adExtendCity\":\"\"}","hrInfoType":0,"isRemoteWork":false,"contactAllowed":"0","contactDay":"","contactTime":"","hasHrMobile":true,"jobTagsForOrder":["3-4年","本科","培训","办公软件","招聘","谈判","人事","网络","培训计划","法律法规","简历筛选","猎头","定期体检","员工旅游","餐饮补贴","五险一金","年终奖金","生日福利"],"isAllowChat":true,"sesameLabelList":[{"labelName":"国企供应商","labelCode":"gov_owned_supplier","labelDefinition":"经芝麻通过公开数据识别，该企业过去1年曾中标国企单位的招标项目。属于中广核环保产业有限公司供应商，其具有较高的资金实力和经营能力。"},{"labelName":"政府供应商","labelCode":"gov_supplier","labelDefinition":"经芝麻通过公开数据识别，经芝麻通过公开数据识别，企业过去1年曾中标政府机构的招标项目。属于政府机构的供应商，其具有较高的资金实力和经营能力。"},{"labelName":"A级纳税人","labelCode":"a_taxpayer","labelDefinition":"评定年份:2022。税务部门采用年度评价指标得分和直接判级相结合的方式，依据纳税人信用历史信息、税务内部信息和外部信息等内容对纳税人进行信用评价，按照信用程度设为A、B、C、D四级，A级纳税人是税务部门评定的纳税信用级别最高的纳税人。"}],"jobWelfareCodeDataList":[{"code":"100838","chineseTitle":"定期体检","englishTitle":"","typeCode":"10035","typeTitle":"福利待遇"},{"code":"100828","chineseTitle":"员工旅游","englishTitle":"","typeCode":"10035","typeTitle":"福利待遇"},{"code":"100830","chineseTitle":"餐饮补贴","englishTitle":"","typeCode":"10035","typeTitle":"福利待遇"},{"code":"100234","chineseTitle":"五险一金","englishTitle":"","typeCode":"10035","typeTitle":"福利待遇"},{"code":"100835","chineseTitle":"年终奖金","englishTitle":"","typeCode":"10035","typeTitle":"福利待遇"},{"code":"100854","chineseTitle":"生日福利","englishTitle":"","typeCode":"10035","typeTitle":"福利待遇"}],"jobSalaryMax":"13000","jobSalaryMin":"9000","jobScheme":"qiancheng://home/show_job_info?jobid=151497515&property=%7B%22isInitiative%22%3A%22%E6%98%AF%22%2C%22pageCode%22%3A%22sou%7Csou%7Csoulb%22%2C%22shortPageCode%22%3A%22sou%7Csou%7Csoulb%22%2C%22searchType%22%3A%22%E6%89%8B%E5%8A%A8%E6%90%9C%E7%B4%A2%E8%81%8C%E4%BD%8D%22%2C%22jobRank%22%3A%22207%22%2C%22policyId%22%3A%22%7B%5C%22layer_rank_v23%5C%22%3A%5C%222099_2%5C%22%7D%22%2C%22keyword%22%3A%22%22%2C%22pageNum%22%3A%2211%22%2C%22requestId%22%3A%22e63cdc1f7d86113e02a5c0762d22acc8%22%2C%22jobType%22%3A%220%22%7D","coId":"3015116"},{"property":"{\"isInitiative\":\"是\",\"pageCode\":\"sou|sou|soulb\",\"shortPageCode\":\"sou|sou|soulb\",\"searchType\":\"手动搜索职位\",\"jobRank\":\"208\",\"policyId\":\"{\\\"layer_rank_v23\\\":\\\"2099_2\\\"}\",\"keyword\":\"\",\"pageNum\":\"11\",\"requestId\":\"e63cdc1f7d86113e02a5c0762d22acc8\",\"jobType\":\"0\"}","jobId":"153814910","jobType":"0","jobName":"人事招聘专员","jobTags":["1年及以上","本科","五险一金","餐饮补贴","年终奖金","定期体检","通讯补贴","节日福利","福利假期"],"jobNumString":"","workAreaCode":"020000","jobAreaCode":"020000","jobAreaString":"上海","hrefAreaPinYin":"shanghai","jobAreaLevelDetail":{"provinceCode":"020000","provinceString":"上海","cityCode":"020000","cityString":"上海","landMarkString":""},"provideSalaryString":"8千-1万·15薪","issueDateString":"2024-04-15 11:34:06","confirmDateString":"2024-03-15 09:46:40","workYear":"3","workYearString":"1年及以上","degreeString":"本科","industryType1":"51","industryType2":"51","industryType1Str":"物业管理/商业中心","industryType2Str":"物业管理/商业中心","funcType1Code":"0604","funcType2Code":"","major1Str":"","major2Str":"","encCoId":"BmhUNFM2UmtUNlQ-UzA","companyName":"上海嵩霖商业管理","fullCompanyName":"上海嵩霖商业管理有限公司","companyLogo":"https://img04.51jobcdn.com/im/mkt/app/51job_phone/app/homelogo/new/home_logo_default_management.png","companyTypeString":"民营","companySizeString":"","companySizeCode":"","companyIndustryType1Str":"物业管理/商业中心","companyIndustryType2Str":"物业管理/商业中心","hrUid":"19656749","hrName":"Monica","smallHrLogoUrl":"http://img01.51jobcdn.com/imehire/userportrait/default/li_portrait_female_006_small.png","hrPosition":"HRM","hrMedalTitle":"","hrMedalLevel":"","showHrMedalTitle":true,"hrIsOnline":false,"isOnline":false,"hrLabels":["今日活跃"],"updateDateTime":"2024-03-15 09:48:40","lon":"121.430453","lat":"31.205302","isCommunicate":false,"isFromXyx":false,"isIntern":false,"isModelEmployer":false,"isQuickFeedback":false,"isPromotion":false,"isApply":false,"isExpire":false,"jobHref":"https://jobs.51job.com/shanghai/153814910.html?s=sou_sou_soulb&t=0_0&req=e63cdc1f7d86113e02a5c0762d22acc8","jobDescribe":"职位描述：\r\n1、招聘职位的发布、简历的筛选及面试\r\n2、Offer发放及相关背景调查、信息资料收集及核实等\r\n3、按需完成相关人力资源报表；\r\n4、员工试用期转正、入离职手续的跟进办理\r\n5、员工居住证积分、落户等人事事务性工作\r\n6、内部人事政策的咨询与解答\r\n任职资格：\r\n1、大学本科及以上学历；\r\n2、1年以上招聘相关工作经验，有商业地产从业经验优先；\r\n3、细心有耐心，抗压性强。","companyHref":"https://jobs.51job.com/all/coBmhUNFM2UmtUNlQ-UzA.html","allowChatOnline":false,"ctmId":7482182,"term":"0","termStr":"全职","landmarkId":"","landmarkString":"","retrieverName":"JobTermBasedRetriever","exrInfo02":"{\"retrieverName\":\"JobTermBasedRetriever\",\"referJobId\":\"\",\"intentions\":\"\",\"adExtendFunc\":\"\",\"adExtendCity\":\"\"}","hrInfoType":0,"isRemoteWork":false,"contactAllowed":"0","contactDay":"","contactTime":"","hasHrMobile":true,"jobTagsForOrder":["1年及以上","本科","五险一金","餐饮补贴","年终奖金","定期体检","通讯补贴","节日福利","福利假期"],"isAllowChat":true,"sesameLabelList":[{"labelName":"绝对控股1家公司","labelCode":"absolute_holding_companies","labelDefinition":"该企业绝对控股1公司，绝对控股是指出资额占有限责任公司资本总额百分之六十七以上或者其持有的股份占股份有限公司股本总额百分之六十七以上。"}],"jobWelfareCodeDataList":[{"code":"100234","chineseTitle":"五险一金","englishTitle":"","typeCode":"10035","typeTitle":"福利待遇"},{"code":"100830","chineseTitle":"餐饮补贴","englishTitle":"","typeCode":"10035","typeTitle":"福利待遇"},{"code":"100835","chineseTitle":"年终奖金","englishTitle":"","typeCode":"10035","typeTitle":"福利待遇"},{"code":"100838","chineseTitle":"定期体检","englishTitle":"","typeCode":"10035","typeTitle":"福利待遇"},{"code":"100831","chineseTitle":"通讯补贴","englishTitle":"","typeCode":"10035","typeTitle":"福利待遇"},{"code":"100842","chineseTitle":"节日福利","englishTitle":"","typeCode":"10035","typeTitle":"福利待遇"}],"jobSalaryMax":"10000","jobSalaryMin":"8000","jobScheme":"qiancheng://home/show_job_info?jobid=153814910&property=%7B%22isInitiative%22%3A%22%E6%98%AF%22%2C%22pageCode%22%3A%22sou%7Csou%7Csoulb%22%2C%22shortPageCode%22%3A%22sou%7Csou%7Csoulb%22%2C%22searchType%22%3A%22%E6%89%8B%E5%8A%A8%E6%90%9C%E7%B4%A2%E8%81%8C%E4%BD%8D%22%2C%22jobRank%22%3A%22208%22%2C%22policyId%22%3A%22%7B%5C%22layer_rank_v23%5C%22%3A%5C%222099_2%5C%22%7D%22%2C%22keyword%22%3A%22%22%2C%22pageNum%22%3A%2211%22%2C%22requestId%22%3A%22e63cdc1f7d86113e02a5c0762d22acc8%22%2C%22jobType%22%3A%220%22%7D","coId":"8467796"},{"property":"{\"isInitiative\":\"是\",\"pageCode\":\"sou|sou|soulb\",\"shortPageCode\":\"sou|sou|soulb\",\"searchType\":\"手动搜索职位\",\"jobRank\":\"209\",\"policyId\":\"{\\\"layer_rank_v23\\\":\\\"2099_2\\\"}\",\"keyword\":\"\",\"pageNum\":\"11\",\"requestId\":\"e63cdc1f7d86113e02a5c0762d22acc8\",\"jobType\":\"0\"}","jobId":"150102004","jobType":"0","jobName":"行政人事专员","jobTags":["3-4年","本科","excel","招聘","word","ppt","人力资源","信息录入","五险一金","定期体检","专业培训","周末双休","带薪年假","做五休二"],"jobNumString":"","workAreaCode":"020300","jobAreaCode":"020000","jobAreaString":"上海·徐汇区","hrefAreaPinYin":"shanghai-xhq","jobAreaLevelDetail":{"provinceCode":"020000","provinceString":"上海","cityCode":"020000","cityString":"上海","districtString":"徐汇区","landMarkString":"徐家汇"},"provideSalaryString":"8千-1.2万·13薪","issueDateString":"2024-04-14 15:51:47","confirmDateString":"2024-04-14 15:51:47","workYear":"5","workYearString":"3-4年","degreeString":"本科","industryType1":"43","industryType2":"43","industryType1Str":"保险","industryType2Str":"保险","funcType1Code":"0604","funcType2Code":"","major1Str":"","major2Str":"","encCoId":"UzdTMV88Aj8GZ1E2BWg","companyName":"江泰保险经纪股份有限公司华东","fullCompanyName":"江泰保险经纪股份有限公司华东分公司","companyLogo":"https://img04.51jobcdn.com/im/mkt/app/51job_phone/app/homelogo/home_logo_default.png","companyTypeString":"国企","companySizeString":"50-150人","companySizeCode":"2","companyIndustryType1Str":"保险","companyIndustryType2Str":"保险","hrUid":"1824485","hrName":"江泰HR","smallHrLogoUrl":"http://img01.51jobcdn.com/imehire/userportrait/default/li_portrait_la_07_small.png","hrPosition":"人事","hrMedalTitle":"","hrMedalLevel":"","showHrMedalTitle":true,"hrIsOnline":false,"isOnline":false,"hrLabels":["今日活跃"],"updateDateTime":"2024-04-14 15:51:47","lon":"121.466962","lat":"31.208433","isCommunicate":false,"isFromXyx":false,"isIntern":false,"isModelEmployer":false,"isQuickFeedback":true,"isPromotion":false,"isApply":false,"isExpire":false,"jobHref":"https://jobs.51job.com/shanghai-xhq/150102004.html?s=sou_sou_soulb&t=0_0&req=e63cdc1f7d86113e02a5c0762d22acc8","jobDescribe":"工作职责：\r\n1.负责公司招聘工作：职位说明的撰写、选择合适的招聘渠道发布职位、简历筛选、初试和后续面试进程的推进和反馈；招聘相关信息的统计和分析工作；维护网络招聘平台和人才供应商关系；\r\n2.负责公司新员工入职管理工作：新员工入职前的准备工作、入职当天的引荐及员工入职资料的收集；试用期员工情况跟进、试用期考核管理；负责公司人员信息管理工作：员工信息的录入、更新；维护月、季、年度的人员信息统计和分析报表；\r\n3.负责行政人事部门流程的各项流转以及执行；\r\n4.其它人事行政相关的协助工作：劳动合同管理、人员档案管理、社保公积金管理、考勤统计、培训现场组织、员工关系处理、规章制度公司撰写、员工活动筹备、重大会议准备、费用报销管理等；\r\n5.上级领导交办的其它部门内工作\r\n职位要求：\r\n1.学历要求：统招本科及以上学历，人力资源专业、法律专业、劳动保障专业及相关专业优先考虑；\r\n2.工作经验：3年及以上人事工作经验；\r\n3.职业技能：有人力资源相关证书者优先考虑，熟悉劳动法律法规及国家地方用工政策、了解各地社保公积金操作，精通Word/Excel/PPT等办公软件操作（硬性条件）；","companyHref":"https://jobs.51job.com/all/coUzdTMV88Aj8GZ1E2BWg.html","allowChatOnline":false,"ctmId":1520973,"term":"0","termStr":"全职","landmarkId":"66","landmarkString":"徐家汇","retrieverName":"JobTermBasedRetriever","exrInfo02":"{\"retrieverName\":\"JobTermBasedRetriever\",\"referJobId\":\"\",\"intentions\":\"\",\"adExtendFunc\":\"\",\"adExtendCity\":\"\"}","hrInfoType":0,"isRemoteWork":false,"contactAllowed":"","contactDay":"","contactTime":"","hasHrMobile":true,"jobTagsForOrder":["3-4年","本科","excel","招聘","word","ppt","人力资源","信息录入","五险一金","定期体检","专业培训","周末双休","带薪年假","做五休二"],"isAllowChat":true,"sesameLabelList":[{"labelName":"政府供应商","labelCode":"gov_supplier","labelDefinition":"经芝麻通过公开数据识别，经芝麻通过公开数据识别，企业过去1年曾中标政府机构的招标项目。属于政府机构的供应商，其具有较高的资金实力和经营能力。"},{"labelName":"经营年限全省同行前10%","labelCode":"top_province","labelDefinition":"据工商登记信息显示，该企业相比其他同行业更早进入市场。"},{"labelName":"大学生就业贡献","labelCode":"college_employment_contribution","labelDefinition":"据公开网络招聘信息显示，该企业在近1年内有发布过大学生就业岗位，助力大学生就业。"}],"jobWelfareCodeDataList":[{"code":"100234","chineseTitle":"五险一金","englishTitle":"","typeCode":"10035","typeTitle":"福利待遇"},{"code":"100838","chineseTitle":"定期体检","englishTitle":"","typeCode":"10035","typeTitle":"福利待遇"},{"code":"100832","chineseTitle":"专业培训","englishTitle":"","typeCode":"10035","typeTitle":"福利待遇"},{"code":"100841","chineseTitle":"周末双休","englishTitle":"","typeCode":"10035","typeTitle":"福利待遇"},{"code":"100843","chineseTitle":"带薪年假","englishTitle":"","typeCode":"10035","typeTitle":"福利待遇"}],"jobSalaryMax":"12000","jobSalaryMin":"8000","jobScheme":"qiancheng://home/show_job_info?jobid=150102004&property=%7B%22isInitiative%22%3A%22%E6%98%AF%22%2C%22pageCode%22%3A%22sou%7Csou%7Csoulb%22%2C%22shortPageCode%22%3A%22sou%7Csou%7Csoulb%22%2C%22searchType%22%3A%22%E6%89%8B%E5%8A%A8%E6%90%9C%E7%B4%A2%E8%81%8C%E4%BD%8D%22%2C%22jobRank%22%3A%22209%22%2C%22policyId%22%3A%22%7B%5C%22layer_rank_v23%5C%22%3A%5C%222099_2%5C%22%7D%22%2C%22keyword%22%3A%22%22%2C%22pageNum%22%3A%2211%22%2C%22requestId%22%3A%22e63cdc1f7d86113e02a5c0762d22acc8%22%2C%22jobType%22%3A%220%22%7D","coId":"2603448"},{"property":"{\"isInitiative\":\"是\",\"pageCode\":\"sou|sou|soulb\",\"shortPageCode\":\"sou|sou|soulb\",\"searchType\":\"手动搜索职位\",\"jobRank\":\"210\",\"policyId\":\"{\\\"layer_rank_v23\\\":\\\"2099_2\\\"}\",\"keyword\":\"\",\"pageNum\":\"11\",\"requestId\":\"e63cdc1f7d86113e02a5c0762d22acc8\",\"jobType\":\"0\"}","jobId":"154351028","jobType":"0","jobName":"人事服务专员","jobTags":["1-3年","本科","五险一金","免费工作餐"],"jobNumString":"","workAreaCode":"021500","jobAreaCode":"020000","jobAreaString":"上海·松江区","hrefAreaPinYin":"shanghai-sjq","jobAreaLevelDetail":{"provinceCode":"020000","provinceString":"上海","cityCode":"020000","cityString":"上海","districtString":"松江区","landMarkString":"松江大学城"},"provideSalaryString":"7-9千","issueDateString":"2024-04-12 15:59:12","confirmDateString":"2024-04-12 15:59:12","workYear":"3","workYearString":"1-3年","degreeString":"本科","industryType1":"44","industryType2":"","industryType1Str":"家具/家电/玩具/礼品","industryType2Str":"","funcType1Code":"0604","funcType2Code":"","major1Str":"人力资源管理","major2Str":"","encCoId":"BWEGYFUxBDICYwFlUDw","companyName":"上海飞科电器","fullCompanyName":"上海飞科电器股份有限公司","companyLogo":"https://img01.51jobcdn.com/fansImg/CompLogo/3/2279/2278479/2278479_300.png?637077615459619931","companyTypeString":"已上市","companySizeString":"1000-5000人","companySizeCode":"5","companyIndustryType1Str":"家具/家电/玩具/礼品","hrUid":"19277156","hrName":"焦先生","smallHrLogoUrl":"http://img01.51jobcdn.com/imehire/userportrait/20/19278/19277156/1707035037680_small.png?1707035038","hrPosition":"HR","hrActiveStatusGreen":"刚刚活跃","hrMedalTitle":"","hrMedalLevel":"","showHrMedalTitle":true,"hrIsOnline":false,"isOnline":false,"hrLabels":["1天内处理简历"],"updateDateTime":"2024-04-24 19:52:34","lon":"121.274389","lat":"31.057403","isCommunicate":false,"isFromXyx":false,"isIntern":false,"isModelEmployer":false,"isQuickFeedback":true,"isPromotion":false,"isApply":false,"isExpire":false,"jobHref":"https://jobs.51job.com/shanghai-sjq/154351028.html?s=sou_sou_soulb&t=0_0&req=e63cdc1f7d86113e02a5c0762d22acc8","jobDescribe":"岗位职责：\n1、负责薪酬福利的核算及发放，五险一金的申报及缴纳；\n2、负责员工入、离职手续办理工作，以及相关材料档案归档；\n3、负责员工调动、转正、晋升、降职等手续办理工作，相关资料及时归档；\n4、协助开展公司招聘、培训等工作；\n5、领导交办的其他事务。\n\n岗位要求：\n1、学历/经验：全日制本科及以上学历，人力资源管理等相关专业优先，1年及以上制造业SSC工作经验；\n2、知识/技能：熟练使用Excel、Word等办公软件；\n3、素质/能力：逻辑清晰，沟通表达流利，有较强的执行力。","companyHref":"https://jobs.51job.com/all/coBWEGYFUxBDICYwFlUDw.html","allowChatOnline":false,"ctmId":1231942,"term":"0","termStr":"全职","landmarkId":"2743","landmarkString":"松江大学城","retrieverName":"JobTermBasedRetriever","exrInfo02":"{\"retrieverName\":\"JobTermBasedRetriever\",\"referJobId\":\"\",\"intentions\":\"\",\"adExtendFunc\":\"\",\"adExtendCity\":\"\"}","hrInfoType":0,"isRemoteWork":false,"contactAllowed":"0","contactDay":"","contactTime":"","hasHrMobile":true,"jobTagsForOrder":["1-3年","本科","五险一金","免费工作餐"],"isAllowChat":true,"sesameLabelList":[{"labelName":"A股上市","labelCode":"listed_enterprise","labelDefinition":"该企业在中国证券交易所公开发行企业股票。"},{"labelName":"高新技术企业","labelCode":"high_new_tech_corp","labelDefinition":"发布时间:2023-11-15,评定有效期:3年,颁发机构:全国高新技术企业认定管理工作领导小组办公室。符合《高新技术企业认定管理办法》规定，符合国家重点支持的高新技术领域，持续进行研究开发与技术成果转化，形成企业核心自主知识产权，并以此为基础开展经营活动，在中国境内（不包括港、澳、台地区）注册成立一年以上的居民企业。"},{"labelName":"创新型中小企业","labelCode":"innovative_sme","labelDefinition":"发布时间:2023-03-15,评定有效期:3年,颁发机构:上海市经济和信息化委员会。企业符合《优质中小企业梯度培育管理暂行办法》中创新型中小企业的认定条件，说明企业在技术、管理、市场和组织等方面具备较强的创新能力和发展潜力。"}],"jobWelfareCodeDataList":[{"code":"100234","chineseTitle":"五险一金","englishTitle":"","typeCode":"10035","typeTitle":"福利待遇"}],"jobSalaryMax":"9000","jobSalaryMin":"7000","jobScheme":"qiancheng://home/show_job_info?jobid=154351028&property=%7B%22isInitiative%22%3A%22%E6%98%AF%22%2C%22pageCode%22%3A%22sou%7Csou%7Csoulb%22%2C%22shortPageCode%22%3A%22sou%7Csou%7Csoulb%22%2C%22searchType%22%3A%22%E6%89%8B%E5%8A%A8%E6%90%9C%E7%B4%A2%E8%81%8C%E4%BD%8D%22%2C%22jobRank%22%3A%22210%22%2C%22policyId%22%3A%22%7B%5C%22layer_rank_v23%5C%22%3A%5C%222099_2%5C%22%7D%22%2C%22keyword%22%3A%22%22%2C%22pageNum%22%3A%2211%22%2C%22requestId%22%3A%22e63cdc1f7d86113e02a5c0762d22acc8%22%2C%22jobType%22%3A%220%22%7D","coId":"2278479"},{"property":"{\"isInitiative\":\"是\",\"pageCode\":\"sou|sou|soulb\",\"shortPageCode\":\"sou|sou|soulb\",\"searchType\":\"手动搜索职位\",\"jobRank\":\"211\",\"policyId\":\"{\\\"layer_rank_v23\\\":\\\"2099_2\\\"}\",\"keyword\":\"\",\"pageNum\":\"11\",\"requestId\":\"e63cdc1f7d86113e02a5c0762d22acc8\",\"jobType\":\"0\"}","jobId":"154218990","jobType":"0","jobName":"人力资源专员","jobTags":["5年及以上","本科","五险一金","餐饮补贴","绩效奖金"],"jobNumString":"","workAreaCode":"021800","jobAreaCode":"020000","jobAreaString":"上海·奉贤区","hrefAreaPinYin":"shanghai-fxq","jobAreaLevelDetail":{"provinceCode":"020000","provinceString":"上海","cityCode":"020000","cityString":"上海","districtString":"奉贤区","landMarkString":""},"provideSalaryString":"9千-1.2万·16薪","issueDateString":"2024-04-12 09:05:57","confirmDateString":"2024-04-07 11:51:54","workYear":"6","workYearString":"5年及以上","degreeString":"本科","industryType1":"65","industryType2":"65","industryType1Str":"汽车零配件","industryType2Str":"汽车零配件","funcType1Code":"0604","funcType2Code":"","major1Str":"","major2Str":"","encCoId":"VDRTMVE1Um1TMAxvVjo","companyName":"长春富维东阳汽车零部件","fullCompanyName":"长春富维东阳汽车零部件有限公司","companyLogo":"https://img01.51jobcdn.com/fansImg/CompLogo/7/6672/6671609/6671609_300.jpg?637714669333656928","companyTypeString":"国企","companySizeString":"1000-5000人","companySizeCode":"5","companyIndustryType1Str":"汽车零配件","companyIndustryType2Str":"汽车零配件","hrUid":"18410865","hrName":"费女士","smallHrLogoUrl":"http://img01.51jobcdn.com/imehire/userportrait/default/li_portrait_female_004_small.png","hrPosition":"人力资源","hrMedalTitle":"新锐招聘官","hrMedalLevel":"1","showHrMedalTitle":true,"hrIsOnline":false,"isOnline":false,"hrLabels":["简历处理快"],"updateDateTime":"2024-04-09 14:44:18","lon":"121.761433","lat":"30.908368","isCommunicate":false,"isFromXyx":false,"isIntern":false,"isModelEmployer":false,"isQuickFeedback":false,"isPromotion":false,"isApply":false,"isExpire":false,"jobHref":"https://jobs.51job.com/shanghai-fxq/154218990.html?s=sou_sou_soulb&t=0_0&req=e63cdc1f7d86113e02a5c0762d22acc8","jobDescribe":"工作职责:\n1、基于《招聘和雇佣程序》《一般专业技术管理岗位招聘工作指导书》《生产操作服务岗位招聘工作指导书》落实不同类型岗位的岗位的招聘流程，确保人事任用合规；\t\t\t\t\n2、基于校园招聘整体规划要求，协助总部完成子公司的校园招聘工作（校招计划制定、高校资源获取、校招行程确定、实施校招），完成校招指标；\t\t\t\t\n3、依据《考勤管理工作指导书》《请假管理工作指导书》落实各项考勤管理工作：日常监控考勤数据，及时提供改善策略；审核考勤汇总表，对考勤异常及时提出处理意见，定期进行考勤管理流程风险自查、不定时组织考勤稽核；考勤数；\n4、根据处理（统计、核准、汇总、报审），为工资计算提供准确的数据；\t\t\t\t\n5、员工入、离职手续办理、人事档案管理并及时在人员信息表中做维护，定期对离职率进行分析，输出改善报告，确保离职流程合规、离职材料齐全，\t\t\t\t\n6、合同管理：负责员工（正式、劳务）合同的签订、发放与续签，并妥善保管合同原件，负责合同台账的管理；\t\t\t\t\n7、按照《员工提升和转岗程序》《员工岗位变动工作指导书》落实内部岗位异动及转岗流程，确保转岗工作合规；\t\t\t\t\n8、体系审核：确保各项作业流程符合体系管理要求，做好档案管理，依据体系审核安排，接受并配合内审、外审；\t\t\t\t\n9、遵守公司安全管理规定，贯彻落实环保、职业健康及安全相关法律法规；\t\t\t\t\n10、遵照公司《持续改进项目工作指导书》落实各项持续改进工作的要求，贯彻推进个人改善项目的立项、过程实施、成果输出等工作。\n任职资格:\n1、人力资源管理六大模块基础知识\n2、掌握有关绩效、考勤、人事管理的各项规章制度\n3、熟悉人力资源管理相关法律法规\n4、5年以上人力资源相关经验","companyHref":"https://jobs.51job.com/all/coVDRTMVE1Um1TMAxvVjo.html","allowChatOnline":false,"ctmId":5730318,"term":"0","termStr":"全职","landmarkId":"","landmarkString":"","retrieverName":"JobTermBasedRetriever","exrInfo02":"{\"retrieverName\":\"JobTermBasedRetriever\",\"referJobId\":\"\",\"intentions\":\"\",\"adExtendFunc\":\"\",\"adExtendCity\":\"\"}","hrInfoType":0,"isRemoteWork":false,"contactAllowed":"0","contactDay":"","contactTime":"","hasHrMobile":true,"jobTagsForOrder":["5年及以上","本科","五险一金","餐饮补贴","绩效奖金"],"isAllowChat":true,"sesameLabelList":[{"labelName":"上市企业子公司","labelCode":"stock_market_child","labelDefinition":"经芝麻通过公开数据识别，企业为一汽富维子公司。"},{"labelName":"高新技术企业","labelCode":"high_new_tech_corp","labelDefinition":"发布时间:2022-11-29,评定有效期:3年,颁发机构:全国高新技术企业认定管理工作领导小组办公室。符合《高新技术企业认定管理办法》规定，符合国家重点支持的高新技术领域，持续进行研究开发与技术成果转化，形成企业核心自主知识产权，并以此为基础开展经营活动，在中国境内（不包括港、澳、台地区）注册成立一年以上的居民企业。"},{"labelName":"国家知识产权优势企业","labelCode":"nation_intellectual_advantege_corp","labelDefinition":"发布时间:2022-10-27,评定有效期:3年,颁发机构:国家知识产权局。根据国知发管字〔2013〕36号文件为依据，国家知识产权优势企业拥有自主知识产权和知名品牌、国际竞争力较强，且知识产权管理体系相对完善、知识产权数量和质量大幅提升、知识产权保护能力明显增强、市场竞争力显著提高的企业。"}],"jobWelfareCodeDataList":[{"code":"100234","chineseTitle":"五险一金","englishTitle":"","typeCode":"10035","typeTitle":"福利待遇"},{"code":"100830","chineseTitle":"餐饮补贴","englishTitle":"","typeCode":"10035","typeTitle":"福利待遇"},{"code":"100834","chineseTitle":"绩效奖金","englishTitle":"","typeCode":"10035","typeTitle":"福利待遇"}],"jobSalaryMax":"12000","jobSalaryMin":"9000","jobScheme":"qiancheng://home/show_job_info?jobid=154218990&property=%7B%22isInitiative%22%3A%22%E6%98%AF%22%2C%22pageCode%22%3A%22sou%7Csou%7Csoulb%22%2C%22shortPageCode%22%3A%22sou%7Csou%7Csoulb%22%2C%22searchType%22%3A%22%E6%89%8B%E5%8A%A8%E6%90%9C%E7%B4%A2%E8%81%8C%E4%BD%8D%22%2C%22jobRank%22%3A%22211%22%2C%22policyId%22%3A%22%7B%5C%22layer_rank_v23%5C%22%3A%5C%222099_2%5C%22%7D%22%2C%22keyword%22%3A%22%22%2C%22pageNum%22%3A%2211%22%2C%22requestId%22%3A%22e63cdc1f7d86113e02a5c0762d22acc8%22%2C%22jobType%22%3A%220%22%7D","coId":"6671609"},{"property":"{\"isInitiative\":\"是\",\"pageCode\":\"sou|sou|soulb\",\"shortPageCode\":\"sou|sou|soulb\",\"searchType\":\"手动搜索职位\",\"jobRank\":\"212\",\"policyId\":\"{\\\"layer_rank_v23\\\":\\\"2099_2\\\"}\",\"keyword\":\"\",\"pageNum\":\"11\",\"requestId\":\"e63cdc1f7d86113e02a5c0762d22acc8\",\"jobType\":\"0\"}","jobId":"153904174","jobType":"0","jobName":"HR人力资源岗","jobTags":["2-5年","本科","五险一金","年终奖金","周末双休"],"jobNumString":"","workAreaCode":"020000","jobAreaCode":"020000","jobAreaString":"上海","hrefAreaPinYin":"shanghai","jobAreaLevelDetail":{"provinceCode":"020000","provinceString":"上海","cityCode":"020000","cityString":"上海","landMarkString":""},"provideSalaryString":"1.4-1.6万·13薪","issueDateString":"2024-04-11 21:04:56","confirmDateString":"2024-03-19 17:05:28","workYear":"4","workYearString":"2-5年","degreeString":"本科","industryType1":"07","industryType2":"","industryType1Str":"专业服务(咨询、人力资源、财会)","industryType2Str":"","funcType1Code":"0604","funcType2Code":"","major1Str":"","major2Str":"","encCoId":"B2RQMwBiUWwAZFQw","companyName":"上海外服（集团）","fullCompanyName":"上海外服（集团）有限公司","companyLogo":"https://img01.51jobcdn.com/fansImg/CompLogo/1/572/571317/571317_300.jpg?636716707917592216","companyTypeString":"国企","companySizeString":"1000-5000人","companySizeCode":"5","companyIndustryType1Str":"专业服务(咨询、人力资源、财会)","hrUid":"18966860","hrName":"周浩","smallHrLogoUrl":"http://img01.51jobcdn.com/imehire/userportrait/default/li_portrait_male_003_small.png","hrPosition":"招聘主管","hrMedalTitle":"","hrMedalLevel":"","showHrMedalTitle":true,"hrIsOnline":false,"isOnline":false,"hrLabels":["今日活跃"],"updateDateTime":"2024-04-10 15:51:30","lon":"121.537776","lat":"31.239727","isCommunicate":false,"isFromXyx":false,"isIntern":false,"isModelEmployer":false,"isQuickFeedback":true,"isPromotion":false,"isApply":false,"isExpire":false,"jobHref":"https://jobs.51job.com/shanghai/153904174.html?s=sou_sou_soulb&t=0_0&req=e63cdc1f7d86113e02a5c0762d22acc8","jobDescribe":"1. 招聘管理：根据人力资源规划的要求，组织招聘工作，包括组织部门长提出人员需求、发布招聘信息、筛选简历、组织面试、完成录用程序及转正程序等；\r\n2. 培训管理：收集各部门培训需求，编制年度培训计划，组织培训计划的实施及反馈，建立员工培训档案；\r\n3. 绩效管理：组织月度、年度绩效考核；\r\n4. 员工考勤管理：组织年度年休假计划报送，熟悉各类假期的法律法规，审核员工各类假期及加班认定；\r\n5. 劳动关系管理：办理员工社会保险和公积金，参与各种用工形式的合同签订及结算，办理相关居住证积分、落户、人才公寓及政府住房补贴申请等。\r\n岗位要求：\r\n1. 管理类相关专业，大学本科以上学历；\r\n2. 具有2-5年的人力资源管理相关工作经验；持有人力资源管理职业资格证书优先；\r\n3. 熟练掌握office常用办公软件，具有较好的文字表达和组织协调能力；\r\n4. 身体健康，工作责任心强，有团队精神，为人正直、遵纪守法、爱岗敬业。","companyHref":"https://jobs.51job.com/all/coB2RQMwBiUWwAZFQw.html","allowChatOnline":false,"ctmId":512910,"term":"0","termStr":"全职","landmarkId":"","landmarkString":"","retrieverName":"JobTermBasedRetriever","exrInfo02":"{\"retrieverName\":\"JobTermBasedRetriever\",\"referJobId\":\"\",\"intentions\":\"\",\"adExtendFunc\":\"\",\"adExtendCity\":\"\"}","hrInfoType":0,"isRemoteWork":false,"contactAllowed":"0","contactDay":"","contactTime":"","hasHrMobile":true,"jobTagsForOrder":["2-5年","本科","五险一金","年终奖金","周末双休"],"isAllowChat":true,"sesameLabelList":[{"labelName":"国有企业","labelCode":"state_owned_business","labelDefinition":"该企业为实际控制人为国务院、各地区国有资产监督管理委员会、地方人民政府或机关单位。"},{"labelName":"上市企业子公司","labelCode":"stock_market_child","labelDefinition":"经芝麻通过公开数据识别，企业为外服控股子公司。"},{"labelName":"国企供应商","labelCode":"gov_owned_supplier","labelDefinition":"经芝麻通过公开数据识别，该企业过去1年曾中标国企单位的招标项目。属于工银安盛人寿保险有限公司、华侨城物业（集团）有限公司天津分公司、融通人力资源开发有限公司、北京华侨城物业服务有限公司供应商，其具有较高的资金实力和经营能力。"}],"jobWelfareCodeDataList":[{"code":"100234","chineseTitle":"五险一金","englishTitle":"","typeCode":"10035","typeTitle":"福利待遇"},{"code":"100835","chineseTitle":"年终奖金","englishTitle":"","typeCode":"10035","typeTitle":"福利待遇"},{"code":"100841","chineseTitle":"周末双休","englishTitle":"","typeCode":"10035","typeTitle":"福利待遇"}],"jobSalaryMax":"16000","jobSalaryMin":"14000","jobScheme":"qiancheng://home/show_job_info?jobid=153904174&property=%7B%22isInitiative%22%3A%22%E6%98%AF%22%2C%22pageCode%22%3A%22sou%7Csou%7Csoulb%22%2C%22shortPageCode%22%3A%22sou%7Csou%7Csoulb%22%2C%22searchType%22%3A%22%E6%89%8B%E5%8A%A8%E6%90%9C%E7%B4%A2%E8%81%8C%E4%BD%8D%22%2C%22jobRank%22%3A%22212%22%2C%22policyId%22%3A%22%7B%5C%22layer_rank_v23%5C%22%3A%5C%222099_2%5C%22%7D%22%2C%22keyword%22%3A%22%22%2C%22pageNum%22%3A%2211%22%2C%22requestId%22%3A%22e63cdc1f7d86113e02a5c0762d22acc8%22%2C%22jobType%22%3A%220%22%7D","coId":"571317"},{"property":"{\"isInitiative\":\"是\",\"pageCode\":\"sou|sou|soulb\",\"shortPageCode\":\"sou|sou|soulb\",\"searchType\":\"手动搜索职位\",\"jobRank\":\"213\",\"policyId\":\"{\\\"layer_rank_v23\\\":\\\"2099_2\\\"}\",\"keyword\":\"\",\"pageNum\":\"11\",\"requestId\":\"e63cdc1f7d86113e02a5c0762d22acc8\",\"jobType\":\"0\"}","jobId":"153964829","jobType":"0","jobName":"人事行政主管","jobTags":["3年及以上","本科","五险一金","餐饮补贴","专业培训","绩效奖金","年终奖金","定期体检","带薪年假","节日福利","高温补贴","商业险"],"jobNumString":"","workAreaCode":"021100","jobAreaCode":"020000","jobAreaString":"上海·闵行区","hrefAreaPinYin":"shanghai-mhq","jobAreaLevelDetail":{"provinceCode":"020000","provinceString":"上海","cityCode":"020000","cityString":"上海","districtString":"闵行区","landMarkString":""},"provideSalaryString":"7-8千·13薪","issueDateString":"2024-04-11 15:18:55","confirmDateString":"2024-03-25 16:31:00","workYear":"5","workYearString":"3年及以上","degreeString":"本科","industryType1":"51","industryType2":"51","industryType1Str":"物业管理/商业中心","industryType2Str":"物业管理/商业中心","funcType1Code":"0604","funcType2Code":"","major1Str":"人力资源管理","major2Str":"行政管理","encCoId":"A2BTMF87AzVRNAJpAWw","companyName":"华侨城物业（集团）有限公司上海","fullCompanyName":"华侨城物业（集团）有限公司上海分公司","companyLogo":"https://img04.51jobcdn.com/im/mkt/app/51job_phone/app/homelogo/new/home_logo_default_management.png","companyTypeString":"国企","companySizeString":"150-500人","companySizeCode":"3","companyIndustryType1Str":"物业管理/商业中心","companyIndustryType2Str":"物业管理/商业中心","hrUid":"6435178","hrName":"LE","smallHrLogoUrl":"http://img01.51jobcdn.com/imehire/userportrait/default/li_portrait_male_004_small.png","hrPosition":"招聘主管","hrMedalTitle":"","hrMedalLevel":"","showHrMedalTitle":true,"hrIsOnline":false,"isOnline":false,"hrLabels":["今日活跃"],"updateDateTime":"2024-04-08 15:25:18","lon":"121.506357","lat":"31.112048","isCommunicate":false,"isFromXyx":false,"isIntern":false,"isModelEmployer":false,"isQuickFeedback":false,"isPromotion":false,"isApply":false,"isExpire":false,"jobHref":"https://jobs.51job.com/shanghai-mhq/153964829.html?s=sou_sou_soulb&t=0_0&req=e63cdc1f7d86113e02a5c0762d22acc8","jobDescribe":"工作内容：\n负责公司的人事行政事务，包括员工关系、薪酬福利等方面的工作。\n主要职责：\n1、员工关系：负责公司员工关系维护和解决员工问题。\n2、薪酬福利：负责公司员工的薪酬、福利计划制定和管理，包括薪资结构、绩效考核等。\n3、员工培训：负责公司员工的培训计划制定和管理，包括员工培训需求分析、培训计划制定等。\n4、行政事务：负责公司日常行政事务，包括办公用品采购、公司会议组织等。\n5、其他人事行政工作：负责公司其他人事行政工作的管理和协调.\n职位要求：\n1、本科以上学历，人力资源、行政管理等相关专业背景，3年以上人事行政管理工作经验。\n2、熟悉人力资源管理法规和政策，具备较强的沟通协调能力和逻辑思维能力。\n3、具备良好的抗压能力和团队协作精神，能够独立完成人事行政工作。\n4、熟练掌握办公软件操作，如Word、Excel、PowerPoint等。\n5、了解公司业务流程，具备一定的战略规划和执行能力。","companyHref":"https://jobs.51job.com/all/coA2BTMF87AzVRNAJpAWw.html","allowChatOnline":false,"ctmId":4675545,"term":"0","termStr":"全职","landmarkId":"","landmarkString":"","retrieverName":"JobTermBasedRetriever","exrInfo02":"{\"retrieverName\":\"JobTermBasedRetriever\",\"referJobId\":\"\",\"intentions\":\"\",\"adExtendFunc\":\"\",\"adExtendCity\":\"\"}","hrInfoType":0,"isRemoteWork":false,"contactAllowed":"0","contactDay":"","contactTime":"","hasHrMobile":true,"jobTagsForOrder":["3年及以上","本科","五险一金","餐饮补贴","专业培训","绩效奖金","年终奖金","定期体检","带薪年假","节日福利","高温补贴","商业险"],"isAllowChat":true,"sesameLabelList":[{"labelName":"国企供应商","labelCode":"gov_owned_supplier","labelDefinition":"经芝麻通过公开数据识别，该企业过去1年曾中标国企单位的招标项目。属于华侨城华东投资有限公司供应商，其具有较高的资金实力和经营能力。"},{"labelName":"政府供应商","labelCode":"gov_supplier","labelDefinition":"经芝麻通过公开数据识别，经芝麻通过公开数据识别，企业过去1年曾中标政府机构的招标项目。属于政府机构的供应商，其具有较高的资金实力和经营能力。"},{"labelName":"A级纳税人","labelCode":"a_taxpayer","labelDefinition":"评定年份:2022。税务部门采用年度评价指标得分和直接判级相结合的方式，依据纳税人信用历史信息、税务内部信息和外部信息等内容对纳税人进行信用评价，按照信用程度设为A、B、C、D四级，A级纳税人是税务部门评定的纳税信用级别最高的纳税人。"}],"jobWelfareCodeDataList":[{"code":"100234","chineseTitle":"五险一金","englishTitle":"","typeCode":"10035","typeTitle":"福利待遇"},{"code":"100830","chineseTitle":"餐饮补贴","englishTitle":"","typeCode":"10035","typeTitle":"福利待遇"},{"code":"100832","chineseTitle":"专业培训","englishTitle":"","typeCode":"10035","typeTitle":"福利待遇"},{"code":"100834","chineseTitle":"绩效奖金","englishTitle":"","typeCode":"10035","typeTitle":"福利待遇"},{"code":"100835","chineseTitle":"年终奖金","englishTitle":"","typeCode":"10035","typeTitle":"福利待遇"},{"code":"100838","chineseTitle":"定期体检","englishTitle":"","typeCode":"10035","typeTitle":"福利待遇"},{"code":"100843","chineseTitle":"带薪年假","englishTitle":"","typeCode":"10035","typeTitle":"福利待遇"},{"code":"100842","chineseTitle":"节日福利","englishTitle":"","typeCode":"10035","typeTitle":"福利待遇"},{"code":"100850","chineseTitle":"高温补贴","englishTitle":"","typeCode":"10035","typeTitle":"福利待遇"}],"jobSalaryMax":"8000","jobSalaryMin":"7000","jobScheme":"qiancheng://home/show_job_info?jobid=153964829&property=%7B%22isInitiative%22%3A%22%E6%98%AF%22%2C%22pageCode%22%3A%22sou%7Csou%7Csoulb%22%2C%22shortPageCode%22%3A%22sou%7Csou%7Csoulb%22%2C%22searchType%22%3A%22%E6%89%8B%E5%8A%A8%E6%90%9C%E7%B4%A2%E8%81%8C%E4%BD%8D%22%2C%22jobRank%22%3A%22213%22%2C%22policyId%22%3A%22%7B%5C%22layer_rank_v23%5C%22%3A%5C%222099_2%5C%22%7D%22%2C%22keyword%22%3A%22%22%2C%22pageNum%22%3A%2211%22%2C%22requestId%22%3A%22e63cdc1f7d86113e02a5c0762d22acc8%22%2C%22jobType%22%3A%220%22%7D","coId":"5778088"},{"property":"{\"isInitiative\":\"是\",\"pageCode\":\"sou|sou|soulb\",\"shortPageCode\":\"sou|sou|soulb\",\"searchType\":\"手动搜索职位\",\"jobRank\":\"214\",\"policyId\":\"{\\\"layer_rank_v23\\\":\\\"2099_2\\\"}\",\"keyword\":\"\",\"pageNum\":\"11\",\"requestId\":\"e63cdc1f7d86113e02a5c0762d22acc8\",\"jobType\":\"0\"}","jobId":"141550880","jobType":"0","jobName":"人力资源部副经理（主持工作）","jobTags":["5-7年","本科","五险一金","专业培训","年终奖金","补充公积金","定期体检"],"jobNumString":"","workAreaCode":"020100","jobAreaCode":"020000","jobAreaString":"上海·黄浦区","hrefAreaPinYin":"shanghai-hpq","jobAreaLevelDetail":{"provinceCode":"020000","provinceString":"上海","cityCode":"020000","cityString":"上海","districtString":"黄浦区","landMarkString":""},"provideSalaryString":"24-25万/年","issueDateString":"2024-04-11 13:23:31","confirmDateString":"2024-04-11 10:09:30","workYear":"6","workYearString":"5-7年","degreeString":"本科","industryType1":"51","industryType2":"51","industryType1Str":"物业管理/商业中心","industryType2Str":"物业管理/商业中心","funcType1Code":"0604","funcType2Code":"","major1Str":"","major2Str":"","encCoId":"BmVVMgRuUW4DbwxuUjM","companyName":"上海上勤物业管理","fullCompanyName":"上海上勤物业管理有限公司","companyLogo":"https://img04.51jobcdn.com/im/mkt/app/51job_phone/app/homelogo/new/home_logo_default_management.png","companyTypeString":"国企","companySizeString":"1000-5000人","companySizeCode":"5","companyIndustryType1Str":"物业管理/商业中心","companyIndustryType2Str":"物业管理/商业中心","hrUid":"5671448","hrName":"sqwy7298","smallHrLogoUrl":"http://img01.51jobcdn.com/imehire/userportrait/default/li_portrait_female_002_small.png","hrPosition":"人事招聘","hrMedalTitle":"","hrMedalLevel":"","showHrMedalTitle":true,"hrIsOnline":false,"isOnline":false,"hrLabels":[],"updateDateTime":"2024-04-11 10:09:30","lon":"121.472277","lat":"31.245952","isCommunicate":false,"isFromXyx":false,"isIntern":false,"isModelEmployer":false,"isQuickFeedback":false,"isPromotion":false,"isApply":false,"isExpire":false,"jobHref":"https://jobs.51job.com/shanghai-hpq/141550880.html?s=sou_sou_soulb&t=0_0&req=e63cdc1f7d86113e02a5c0762d22acc8","jobDescribe":"工作内容：\n1、履行总经理室、总经理办公会议和行政会议的决定，完成部门工作目标。\n2、负责开展各项人力资源部工作。\n3、负责管理处员工人事管理工作的指导及监督。\n4、负责公司干部管理、年度考核等工作。\n5、负责公司年度绩效考核、培训计划的具体实施工作及监管指导工作。\n6、负责部门年度工作计划和工作总结的拟定工作。制定各项公司人力资源管理制度、工作流程和规划。\n7、监督指导管理处员工劳动合同签订及劳动纠纷的处理工作。\n8、负责公司核编定员等管理工作。\n9、根据总经理室的要求，适时调整公司的薪酬管理制度、员工管理手册等。10、负责上级集团各类表格的统计、审核、上报；完成集团人力资源部布置的工作。\n11、贯彻公司质量/环境/职业安全健康体系。\n12、履行上级交办的工作。\n\n任职条件：\n1、本科及以上学历，中共党员。\n2、男50周岁以下，女40周岁以下，身体健康。\n3、持有管理类中级职称证书，具有五年以上人力资源管理工作经验，具有较强的沟通、组织、协调及策划能力，有良好的语言表达、写作及文件处理能力。\n4、熟悉人力资源各模块工作，有丰富的实战经验及系统解决问题的能力。\n5、熟悉办公自动化软件操作，熟悉劳动人事法律法规和政策。熟悉物业管理行业者优先。","companyHref":"https://jobs.51job.com/all/coBmVVMgRuUW4DbwxuUjM.html","allowChatOnline":false,"ctmId":4288200,"term":"0","termStr":"全职","landmarkId":"","landmarkString":"","retrieverName":"JobTermBasedRetriever","exrInfo02":"{\"retrieverName\":\"JobTermBasedRetriever\",\"referJobId\":\"\",\"intentions\":\"\",\"adExtendFunc\":\"\",\"adExtendCity\":\"\"}","hrInfoType":0,"isRemoteWork":false,"contactAllowed":"0","contactDay":"","contactTime":"","hasHrMobile":true,"jobTagsForOrder":["5-7年","本科","五险一金","专业培训","年终奖金","补充公积金","定期体检"],"isAllowChat":true,"sesameLabelList":[{"labelName":"国有企业","labelCode":"state_owned_business","labelDefinition":"该企业为实际控制人为国务院、各地区国有资产监督管理委员会、地方人民政府或机关单位。"},{"labelName":"央企供应商","labelCode":"state_owned_supplier","labelDefinition":"经芝麻通过公开数据识别，企业过去1年曾中标中央企业的招标项目。属于中国商飞的供应商，其具有较高的资金实力和经营能力。"},{"labelName":"知名品牌供应商","labelCode":"famous_brand_supplier","labelDefinition":"经芝麻通过公开数据识别，企业过去1年曾中标知名品牌企业的招标项目。属于上海银行供应商、苏宁银河物业供应商、银河物业供应商品牌的供应商，其具有较高的资金实力和经营能力。"}],"jobWelfareCodeDataList":[{"code":"100234","chineseTitle":"五险一金","englishTitle":"","typeCode":"10035","typeTitle":"福利待遇"},{"code":"100832","chineseTitle":"专业培训","englishTitle":"","typeCode":"10035","typeTitle":"福利待遇"},{"code":"100835","chineseTitle":"年终奖金","englishTitle":"","typeCode":"10035","typeTitle":"福利待遇"},{"code":"100826","chineseTitle":"补充公积金","englishTitle":"","typeCode":"10035","typeTitle":"福利待遇"},{"code":"100838","chineseTitle":"定期体检","englishTitle":"","typeCode":"10035","typeTitle":"福利待遇"}],"jobSalaryMax":"","jobSalaryMin":"","jobScheme":"qiancheng://home/show_job_info?jobid=141550880&property=%7B%22isInitiative%22%3A%22%E6%98%AF%22%2C%22pageCode%22%3A%22sou%7Csou%7Csoulb%22%2C%22shortPageCode%22%3A%22sou%7Csou%7Csoulb%22%2C%22searchType%22%3A%22%E6%89%8B%E5%8A%A8%E6%90%9C%E7%B4%A2%E8%81%8C%E4%BD%8D%22%2C%22jobRank%22%3A%22214%22%2C%22policyId%22%3A%22%7B%5C%22layer_rank_v23%5C%22%3A%5C%222099_2%5C%22%7D%22%2C%22keyword%22%3A%22%22%2C%22pageNum%22%3A%2211%22%2C%22requestId%22%3A%22e63cdc1f7d86113e02a5c0762d22acc8%22%2C%22jobType%22%3A%220%22%7D","coId":"5391914"},{"property":"{\"isInitiative\":\"是\",\"pageCode\":\"sou|sou|soulb\",\"shortPageCode\":\"sou|sou|soulb\",\"searchType\":\"手动搜索职位\",\"jobRank\":\"215\",\"policyId\":\"{\\\"layer_rank_v23\\\":\\\"2099_2\\\"}\",\"keyword\":\"\",\"pageNum\":\"11\",\"requestId\":\"e63cdc1f7d86113e02a5c0762d22acc8\",\"jobType\":\"0\"}","jobId":"143342313","jobType":"0","jobName":"人事行政专员","jobTags":["1年","本科","人事相关","五险一金","员工旅游","年终奖金","弹性工作","定期体检","补充医疗保险"],"jobNumString":"","workAreaCode":"021000","jobAreaCode":"020000","jobAreaString":"上海·浦东新区","hrefAreaPinYin":"shanghai-pdxq","jobAreaLevelDetail":{"provinceCode":"020000","provinceString":"上海","cityCode":"020000","cityString":"上海","districtString":"浦东新区","landMarkString":""},"provideSalaryString":"6-8千·14薪","issueDateString":"2024-04-10 09:32:50","confirmDateString":"2023-10-16 11:15:02","workYear":"3","workYearString":"1年","degreeString":"本科","industryType1":"01","industryType2":"02","industryType1Str":"计算机软件","industryType2Str":"电子技术/半导体/集成电路","funcType1Code":"0604","funcType2Code":"","major1Str":"","major2Str":"","encCoId":"UjBXMwdkU2QGYgZlUjE","companyName":"芯和半导体科技（上海）","fullCompanyName":"芯和半导体科技（上海）股份有限公司","companyLogo":"https://img04.51jobcdn.com/im/mkt/app/51job_phone/app/homelogo/new/home_logo_default_software.png","companyTypeString":"民营","companySizeString":"150-500人","companySizeCode":"3","companyIndustryType1Str":"计算机软件","companyIndustryType2Str":"电子技术/半导体/集成电路","hrUid":"17910960","hrName":"Chris","smallHrLogoUrl":"http://img01.51jobcdn.com/imehire/userportrait/default/li_portrait_female_005_small.png","hrPosition":"人事","hrMedalTitle":"","hrMedalLevel":"","showHrMedalTitle":true,"hrIsOnline":false,"isOnline":false,"hrLabels":[],"updateDateTime":"2023-10-16 11:15:02","lon":"121.610344","lat":"31.188889","isCommunicate":false,"isFromXyx":false,"isIntern":false,"isModelEmployer":false,"isQuickFeedback":false,"isPromotion":false,"isApply":false,"isExpire":false,"jobHref":"https://jobs.51job.com/shanghai-pdxq/143342313.html?s=sou_sou_soulb&t=0_0&req=e63cdc1f7d86113e02a5c0762d22acc8","jobDescribe":"岗位职责\n1、协助部门负责人进行人事行政相关管理制度的制定和执行，负责管理人事政策的执行和答疑；\n2、负责协助招聘专员完成简历筛选及约面试等环节，协助完成校招工作\n3、负责应届生、留学生、人才引进等落户、居住证积分及居转户等落户需求；\n4、负责员工商业保险及答疑；\n5、负责组织协调员工完成年度体检；\n7、协助举办团建活动、生日会及年会等企业活动；负责生日礼品等物品采购；负责员工每月零食费用核定请款等；\n8、完成上级交办的其他临时性事务工作。\n\n任职要求：\n1、1年以上相关工作经验；国家统招本科以上学历，不限专业；\n2、具备独立完成人事行政相关事务性工作技能；熟悉劳动法；\n3、有较强的文案功底，工作热情积极、细致耐心、有责任心，具有良好的沟通能力和较强的执行力、抗压力；\n4、熟练操作excel、word、PPT等办公管理软件；","companyHref":"https://jobs.51job.com/all/coUjBXMwdkU2QGYgZlUjE.html","allowChatOnline":false,"ctmId":2902630,"term":"0","termStr":"全职","landmarkId":"","landmarkString":"","retrieverName":"JobTermBasedRetriever","exrInfo02":"{\"retrieverName\":\"JobTermBasedRetriever\",\"referJobId\":\"\",\"intentions\":\"\",\"adExtendFunc\":\"\",\"adExtendCity\":\"\"}","hrInfoType":0,"isRemoteWork":false,"contactAllowed":"","contactDay":"","contactTime":"","hasHrMobile":true,"jobTagsForOrder":["1年","本科","人事相关","五险一金","员工旅游","年终奖金","弹性工作","定期体检","补充医疗保险"],"isAllowChat":true,"sesameLabelList":[{"labelName":"高新技术企业","labelCode":"high_new_tech_corp","labelDefinition":"发布时间:2021-12-23,评定有效期:3年,颁发机构:全国高新技术企业认定管理工作领导小组办公室。符合《高新技术企业认定管理办法》规定，符合国家重点支持的高新技术领域，持续进行研究开发与技术成果转化，形成企业核心自主知识产权，并以此为基础开展经营活动，在中国境内（不包括港、澳、台地区）注册成立一年以上的居民企业。"},{"labelName":"小巨人企业","labelCode":"little_giant_corp","labelDefinition":"评定有效期:3年。企业符合《优质中小企业梯度培育管理暂行办法》中专精特新“小巨人”企业的认定条件，是“专精特新”中小企业中的佼佼者，在中华人民共和国境内工商注册登记、连续经营3年以上，专注于细分市场、创新能力强、市场占有率高、掌握关键核心技术、质量效益优的排头兵企业。"},{"labelName":"创新型中小企业","labelCode":"innovative_sme","labelDefinition":"发布时间:2023-03-15,评定有效期:3年,颁发机构:上海市经济和信息化委员会。企业符合《优质中小企业梯度培育管理暂行办法》中创新型中小企业的认定条件，说明企业在技术、管理、市场和组织等方面具备较强的创新能力和发展潜力。"}],"jobWelfareCodeDataList":[{"code":"100234","chineseTitle":"五险一金","englishTitle":"","typeCode":"10035","typeTitle":"福利待遇"},{"code":"100828","chineseTitle":"员工旅游","englishTitle":"","typeCode":"10035","typeTitle":"福利待遇"},{"code":"100835","chineseTitle":"年终奖金","englishTitle":"","typeCode":"10035","typeTitle":"福利待遇"},{"code":"100837","chineseTitle":"弹性工作","englishTitle":"","typeCode":"10035","typeTitle":"福利待遇"},{"code":"100838","chineseTitle":"定期体检","englishTitle":"","typeCode":"10035","typeTitle":"福利待遇"},{"code":"100825","chineseTitle":"补充医疗保险","englishTitle":"","typeCode":"10035","typeTitle":"福利待遇"}],"jobSalaryMax":"8000","jobSalaryMin":"6000","jobScheme":"qiancheng://home/show_job_info?jobid=143342313&property=%7B%22isInitiative%22%3A%22%E6%98%AF%22%2C%22pageCode%22%3A%22sou%7Csou%7Csoulb%22%2C%22shortPageCode%22%3A%22sou%7Csou%7Csoulb%22%2C%22searchType%22%3A%22%E6%89%8B%E5%8A%A8%E6%90%9C%E7%B4%A2%E8%81%8C%E4%BD%8D%22%2C%22jobRank%22%3A%22215%22%2C%22policyId%22%3A%22%7B%5C%22layer_rank_v23%5C%22%3A%5C%222099_2%5C%22%7D%22%2C%22keyword%22%3A%22%22%2C%22pageNum%22%3A%2211%22%2C%22requestId%22%3A%22e63cdc1f7d86113e02a5c0762d22acc8%22%2C%22jobType%22%3A%220%22%7D","coId":"4009106"},{"property":"{\"isInitiative\":\"是\",\"pageCode\":\"sou|sou|soulb\",\"shortPageCode\":\"sou|sou|soulb\",\"searchType\":\"手动搜索职位\",\"jobRank\":\"216\",\"policyId\":\"{\\\"layer_rank_v23\\\":\\\"2099_2\\\"}\",\"keyword\":\"\",\"pageNum\":\"11\",\"requestId\":\"e63cdc1f7d86113e02a5c0762d22acc8\",\"jobType\":\"0\"}","jobId":"154273169","jobType":"0","jobName":"人事兼行政（外资医疗）","jobTags":["2年及以上","本科","行政","英语","人事","劳动合同签订","付款申请","文档管理","账单核对","居住证","入职流程","五险一金","年终奖金","定期体检","周末双休"],"jobNumString":"","workAreaCode":"020100","jobAreaCode":"020000","jobAreaString":"上海·黄浦区","hrefAreaPinYin":"shanghai-hpq","jobAreaLevelDetail":{"provinceCode":"020000","provinceString":"上海","cityCode":"020000","cityString":"上海","districtString":"黄浦区","landMarkString":""},"provideSalaryString":"8千-1万·13薪","issueDateString":"2024-04-11 21:04:56","confirmDateString":"2024-04-09 14:19:55","workYear":"4","workYearString":"2年及以上","degreeString":"本科","industryType1":"07","industryType2":"","industryType1Str":"专业服务(咨询、人力资源、财会)","industryType2Str":"","funcType1Code":"0604","funcType2Code":"","major1Str":"","major2Str":"","encCoId":"B2RQMwBiUWwAZFQw","companyName":"上海外服（集团）","fullCompanyName":"上海外服（集团）有限公司","companyLogo":"https://img01.51jobcdn.com/fansImg/CompLogo/1/572/571317/571317_300.jpg?636716707917592216","companyTypeString":"国企","companySizeString":"1000-5000人","companySizeCode":"5","companyIndustryType1Str":"专业服务(咨询、人力资源、财会)","hrUid":"18966860","hrName":"周浩","smallHrLogoUrl":"http://img01.51jobcdn.com/imehire/userportrait/default/li_portrait_male_003_small.png","hrPosition":"招聘主管","hrMedalTitle":"","hrMedalLevel":"","showHrMedalTitle":true,"hrIsOnline":false,"isOnline":false,"hrLabels":["今日活跃"],"updateDateTime":"2024-04-10 15:49:04","lon":"121.475365","lat":"31.211885","isCommunicate":false,"isFromXyx":false,"isIntern":false,"isModelEmployer":false,"isQuickFeedback":true,"isPromotion":false,"isApply":false,"isExpire":false,"jobHref":"https://jobs.51job.com/shanghai-hpq/154273169.html?s=sou_sou_soulb&t=0_0&req=e63cdc1f7d86113e02a5c0762d22acc8","jobDescribe":"人事工作70%，法务部行政30%\r\n工作职责：\r\n1. 负责人力资源运营工作，包括支持入职流程，离职流程，文档收集和归档，劳动合同签订，协助员工办理社保/居住证等事宜。\r\n2. 在人事经理的指导下，协助每月工资账单的制作，包括考勤信息录入，工资明细和账单核对，付款申请等。\r\n3. 员工沟通与支持，包括各类员工需要的证明开具，各类沟通信的制作等。\r\n培训以及活动的支持，包括培训筹备，员工活动筹备等。\r\n4. 文档管理，包括人事部和法务部的合同归档及管理。\r\n5. 在法务部负责人的指导下准备、翻译法务文件；支持法务部其他行政事务，如文件扫描与打印。\r\n要求：\r\n1. 本科及以上学历\r\n2. 2年以上人事/工资相关经验\r\n3. 希望候选人认真仔细，聪明伶俐\r\n4. 英语能读能写","companyHref":"https://jobs.51job.com/all/coB2RQMwBiUWwAZFQw.html","allowChatOnline":false,"ctmId":512910,"term":"0","termStr":"全职","landmarkId":"","landmarkString":"","retrieverName":"JobTermBasedRetriever","exrInfo02":"{\"retrieverName\":\"JobTermBasedRetriever\",\"referJobId\":\"\",\"intentions\":\"\",\"adExtendFunc\":\"\",\"adExtendCity\":\"\"}","hrInfoType":0,"isRemoteWork":false,"contactAllowed":"0","contactDay":"","contactTime":"","hasHrMobile":true,"jobTagsForOrder":["2年及以上","本科","行政","英语","人事","劳动合同签订","付款申请","文档管理","账单核对","居住证","入职流程","五险一金","年终奖金","定期体检","周末双休"],"isAllowChat":true,"sesameLabelList":[{"labelName":"国有企业","labelCode":"state_owned_business","labelDefinition":"该企业为实际控制人为国务院、各地区国有资产监督管理委员会、地方人民政府或机关单位。"},{"labelName":"上市企业子公司","labelCode":"stock_market_child","labelDefinition":"经芝麻通过公开数据识别，企业为外服控股子公司。"},{"labelName":"国企供应商","labelCode":"gov_owned_supplier","labelDefinition":"经芝麻通过公开数据识别，该企业过去1年曾中标国企单位的招标项目。属于工银安盛人寿保险有限公司、华侨城物业（集团）有限公司天津分公司、融通人力资源开发有限公司、北京华侨城物业服务有限公司供应商，其具有较高的资金实力和经营能力。"}],"jobWelfareCodeDataList":[{"code":"100234","chineseTitle":"五险一金","englishTitle":"","typeCode":"10035","typeTitle":"福利待遇"},{"code":"100835","chineseTitle":"年终奖金","englishTitle":"","typeCode":"10035","typeTitle":"福利待遇"},{"code":"100838","chineseTitle":"定期体检","englishTitle":"","typeCode":"10035","typeTitle":"福利待遇"},{"code":"100841","chineseTitle":"周末双休","englishTitle":"","typeCode":"10035","typeTitle":"福利待遇"}],"jobSalaryMax":"10000","jobSalaryMin":"8000","jobScheme":"qiancheng://home/show_job_info?jobid=154273169&property=%7B%22isInitiative%22%3A%22%E6%98%AF%22%2C%22pageCode%22%3A%22sou%7Csou%7Csoulb%22%2C%22shortPageCode%22%3A%22sou%7Csou%7Csoulb%22%2C%22searchType%22%3A%22%E6%89%8B%E5%8A%A8%E6%90%9C%E7%B4%A2%E8%81%8C%E4%BD%8D%22%2C%22jobRank%22%3A%22216%22%2C%22policyId%22%3A%22%7B%5C%22layer_rank_v23%5C%22%3A%5C%222099_2%5C%22%7D%22%2C%22keyword%22%3A%22%22%2C%22pageNum%22%3A%2211%22%2C%22requestId%22%3A%22e63cdc1f7d86113e02a5c0762d22acc8%22%2C%22jobType%22%3A%220%22%7D","coId":"571317"},{"property":"{\"isInitiative\":\"是\",\"pageCode\":\"sou|sou|soulb\",\"shortPageCode\":\"sou|sou|soulb\",\"searchType\":\"手动搜索职位\",\"jobRank\":\"217\",\"policyId\":\"{\\\"layer_rank_v23\\\":\\\"2099_2\\\"}\",\"keyword\":\"\",\"pageNum\":\"11\",\"requestId\":\"e63cdc1f7d86113e02a5c0762d22acc8\",\"jobType\":\"0\"}","jobId":"154256716","jobType":"0","jobName":"人事行政","jobTags":["无需经验","本科","行政","人事","日语","弹性工作","免费茶水","意外保险"],"jobNumString":"","workAreaCode":"021000","jobAreaCode":"020000","jobAreaString":"上海·浦东新区","hrefAreaPinYin":"shanghai-pdxq","jobAreaLevelDetail":{"provinceCode":"020000","provinceString":"上海","cityCode":"020000","cityString":"上海","districtString":"浦东新区","landMarkString":""},"provideSalaryString":"8-9千·14薪","issueDateString":"2024-04-08 17:18:37","confirmDateString":"2024-04-08 17:18:37","workYear":"10","workYearString":"无需经验","degreeString":"本科","industryType1":"43","industryType2":"43","industryType1Str":"保险","industryType2Str":"保险","funcType1Code":"0604","funcType2Code":"","major1Str":"","major2Str":"","encCoId":"AWQGZQBjVmEOY1E2Vzo","companyName":"东京海上日动火灾保险（中国）","fullCompanyName":"东京海上日动火灾保险（中国）有限公司","companyLogo":"https://img04.51jobcdn.com/im/mkt/app/51job_phone/app/homelogo/home_logo_default.png","companyTypeString":"外资（非欧美）","companySizeString":"150-500人","companySizeCode":"3","companyIndustryType1Str":"保险","companyIndustryType2Str":"保险","hrUid":"2990132","hrName":"TMNCH","smallHrLogoUrl":"http://img01.51jobcdn.com/imehire/userportrait/default/li_portrait_female_001_small.png","hrPosition":"HR主管","hrMedalTitle":"","hrMedalLevel":"","showHrMedalTitle":true,"hrIsOnline":false,"isOnline":false,"hrLabels":[],"updateDateTime":"2024-04-08 17:20:37","lon":"121.513781","lat":"31.245462","isCommunicate":false,"isFromXyx":false,"isIntern":false,"isModelEmployer":false,"isQuickFeedback":false,"isPromotion":false,"isApply":false,"isExpire":false,"jobHref":"https://jobs.51job.com/shanghai-pdxq/154256716.html?s=sou_sou_soulb&t=0_0&req=e63cdc1f7d86113e02a5c0762d22acc8","jobDescribe":"岗位职责：\n1.负责日常各类行政工作的运营（包括但不限于物资采购、资产管理、社有车管理、费用结算分摊等工作），以及上述相关业务数据的统计汇总；\n2.应对临时性、突发性行政业务诉求。\n\n任职要求：\n1.本科及以上学历（应届生可）\n2.日语N2及以上水平（或英语商务水平）\n3.office办公能力佳\n4.对人事行政工作有热情，有积极主动性\n5.耐心细致、有责任心、正向积极乐观、具备一定的抗压能力\n6.有人事行政工作经验优先","companyHref":"https://jobs.51job.com/all/coAWQGZQBjVmEOY1E2Vzo.html","allowChatOnline":false,"ctmId":2608455,"term":"0","termStr":"全职","landmarkId":"","landmarkString":"","retrieverName":"JobTermBasedRetriever","exrInfo02":"{\"retrieverName\":\"JobTermBasedRetriever\",\"referJobId\":\"\",\"intentions\":\"\",\"adExtendFunc\":\"\",\"adExtendCity\":\"\"}","hrInfoType":0,"isRemoteWork":false,"contactAllowed":"0","contactDay":"","contactTime":"","hasHrMobile":true,"jobTagsForOrder":["无需经验","本科","行政","人事","日语","弹性工作","免费茶水","意外保险"],"isAllowChat":true,"sesameLabelList":[{"labelName":"外商投资企业","labelCode":"foreig_owned_enterprise","labelDefinition":"该企业由外国的自然人、企业或者其他组织投资，依照中国法律在中国境内经登记注册设立。"},{"labelName":"A级纳税人","labelCode":"a_taxpayer","labelDefinition":"评定年份:2022。税务部门采用年度评价指标得分和直接判级相结合的方式，依据纳税人信用历史信息、税务内部信息和外部信息等内容对纳税人进行信用评价，按照信用程度设为A、B、C、D四级，A级纳税人是税务部门评定的纳税信用级别最高的纳税人。"},{"labelName":"2023年Asiabrand亚洲品牌500强","labelCode":"outstanding_brand_3","labelDefinition":"颁发机构:Asiabrand,评定年份:2023。榜单研发是基于从亚洲品牌研究院数据库中筛选出16000个创新型品牌，采用Asiabrand品牌价值评价 3.0“定性+定量”模型，通过对企业品牌资产的精确计量和品牌资产功效的相关分析，使得品牌价值计算结果更加贴近市场价值，为政府管理、投融资、企业资源配置和品牌管理都提供了科学、客观的参考依据。"}],"jobWelfareCodeDataList":[{"code":"100837","chineseTitle":"弹性工作","englishTitle":"","typeCode":"10035","typeTitle":"福利待遇"}],"jobSalaryMax":"9000","jobSalaryMin":"8000","jobScheme":"qiancheng://home/show_job_info?jobid=154256716&property=%7B%22isInitiative%22%3A%22%E6%98%AF%22%2C%22pageCode%22%3A%22sou%7Csou%7Csoulb%22%2C%22shortPageCode%22%3A%22sou%7Csou%7Csoulb%22%2C%22searchType%22%3A%22%E6%89%8B%E5%8A%A8%E6%90%9C%E7%B4%A2%E8%81%8C%E4%BD%8D%22%2C%22jobRank%22%3A%22217%22%2C%22policyId%22%3A%22%7B%5C%22layer_rank_v23%5C%22%3A%5C%222099_2%5C%22%7D%22%2C%22keyword%22%3A%22%22%2C%22pageNum%22%3A%2211%22%2C%22requestId%22%3A%22e63cdc1f7d86113e02a5c0762d22acc8%22%2C%22jobType%22%3A%220%22%7D","coId":"3709848"},{"property":"{\"isInitiative\":\"是\",\"pageCode\":\"sou|sou|soulb\",\"shortPageCode\":\"sou|sou|soulb\",\"searchType\":\"手动搜索职位\",\"jobRank\":\"218\",\"policyId\":\"{\\\"layer_rank_v23\\\":\\\"2099_2\\\"}\",\"keyword\":\"\",\"pageNum\":\"11\",\"requestId\":\"e63cdc1f7d86113e02a5c0762d22acc8\",\"jobType\":\"0\"}","jobId":"154161686","jobType":"0","jobName":"人事专员","jobTags":["无需经验","本科","五险一金","弹性工作制","接收应届生","五险一金","专业培训","弹性工作","周末双休","零食下午茶"],"jobNumString":"","workAreaCode":"020500","jobAreaCode":"020000","jobAreaString":"上海·静安区","hrefAreaPinYin":"shanghai-jaq","jobAreaLevelDetail":{"provinceCode":"020000","provinceString":"上海","cityCode":"020000","cityString":"上海","districtString":"静安区","landMarkString":""},"provideSalaryString":"5-7千","issueDateString":"2024-04-08 11:37:17","confirmDateString":"2024-04-02 11:39:29","workYear":"10","workYearString":"无需经验","degreeString":"本科","industryType1":"51","industryType2":"59","industryType1Str":"物业管理/商业中心","industryType2Str":"外包服务","funcType1Code":"0604","funcType2Code":"","major1Str":"","major2Str":"","encCoId":"CW1VMlIzADcHZFE3BWg","companyName":"爱玛客服务产业（中国）有限公司上海","fullCompanyName":"爱玛客服务产业（中国）有限公司上海分公司","companyLogo":"https://img01.51jobcdn.com/fansImg/CompLogo/3/2330/2329658/2329658_120.gif?636353699071744951","companyTypeString":"外资（欧美）","companySizeString":"10000人以上","companySizeCode":"7","companyIndustryType1Str":"物业管理/商业中心","companyIndustryType2Str":"外包服务","hrUid":"17534897","hrName":"达先生","smallHrLogoUrl":"http://img01.51jobcdn.com/imehire/userportrait/default/li_portrait_female_006_small.png","hrPosition":"HR","hrMedalTitle":"","hrMedalLevel":"","showHrMedalTitle":true,"hrIsOnline":false,"isOnline":false,"hrLabels":[],"updateDateTime":"2024-04-02 11:41:29","lon":"121.446027","lat":"31.284894","isCommunicate":false,"isFromXyx":false,"isIntern":false,"isModelEmployer":false,"isQuickFeedback":false,"isPromotion":false,"isApply":false,"isExpire":false,"jobHref":"https://jobs.51job.com/shanghai-jaq/154161686.html?s=sou_sou_soulb&t=0_0&req=e63cdc1f7d86113e02a5c0762d22acc8","jobDescribe":"人事专员任职条件：\n1、乐观开朗，思维灵活，富有创造力；\n2、具备较强抗压能力，积极向学者优先；\n3、能接受江浙沪出差\n\n职位描述：\n1、拓展招聘渠道，及时高效的完成各层级招聘需求并跟进后续结果；\n2、深入贴近部门的业务进展以及人力现状，成为员工与公司的沟通纽带；\n3、推动公司各项人力资源政策及流程在业务部门的推进与落地执行；\n4、协助团队完成人才培养、员工激励、人事稽核等工作；\n5、完成领导交办的其他工作；\n\n上班时间：早9晚6 做五休二 国家法定节假日休息 实施弹性工作制。","companyHref":"https://jobs.51job.com/all/coCW1VMlIzADcHZFE3BWg.html","allowChatOnline":false,"ctmId":7760,"term":"0","termStr":"全职","landmarkId":"","landmarkString":"","retrieverName":"JobTermBasedRetriever","exrInfo02":"{\"retrieverName\":\"JobTermBasedRetriever\",\"referJobId\":\"\",\"intentions\":\"\",\"adExtendFunc\":\"\",\"adExtendCity\":\"\"}","hrInfoType":0,"isRemoteWork":false,"contactAllowed":"0","contactDay":"","contactTime":"","hasHrMobile":true,"jobTagsForOrder":["无需经验","本科","五险一金","弹性工作制","接收应届生","五险一金","专业培训","弹性工作","周末双休","零食下午茶"],"isAllowChat":true,"sesameLabelList":[{"labelName":"A级纳税人","labelCode":"a_taxpayer","labelDefinition":"评定年份:2022。税务部门采用年度评价指标得分和直接判级相结合的方式，依据纳税人信用历史信息、税务内部信息和外部信息等内容对纳税人进行信用评价，按照信用程度设为A、B、C、D四级，A级纳税人是税务部门评定的纳税信用级别最高的纳税人。"},{"labelName":"经营年限全国同行前5%","labelCode":"top_nationwide","labelDefinition":"据工商登记信息显示，该企业相比其他同行业更早进入市场。"},{"labelName":"大学生就业贡献","labelCode":"college_employment_contribution","labelDefinition":"据公开网络招聘信息显示，该企业在近1年内有发布过大学生就业岗位，助力大学生就业。"}],"jobWelfareCodeDataList":[{"code":"100234","chineseTitle":"五险一金","englishTitle":"","typeCode":"10035","typeTitle":"福利待遇"},{"code":"100832","chineseTitle":"专业培训","englishTitle":"","typeCode":"10035","typeTitle":"福利待遇"},{"code":"100837","chineseTitle":"弹性工作","englishTitle":"","typeCode":"10035","typeTitle":"福利待遇"},{"code":"100841","chineseTitle":"周末双休","englishTitle":"","typeCode":"10035","typeTitle":"福利待遇"},{"code":"100858","chineseTitle":"零食下午茶","englishTitle":"","typeCode":"10035","typeTitle":"福利待遇"}],"jobSalaryMax":"7000","jobSalaryMin":"5000","jobScheme":"qiancheng://home/show_job_info?jobid=154161686&property=%7B%22isInitiative%22%3A%22%E6%98%AF%22%2C%22pageCode%22%3A%22sou%7Csou%7Csoulb%22%2C%22shortPageCode%22%3A%22sou%7Csou%7Csoulb%22%2C%22searchType%22%3A%22%E6%89%8B%E5%8A%A8%E6%90%9C%E7%B4%A2%E8%81%8C%E4%BD%8D%22%2C%22jobRank%22%3A%22218%22%2C%22policyId%22%3A%22%7B%5C%22layer_rank_v23%5C%22%3A%5C%222099_2%5C%22%7D%22%2C%22keyword%22%3A%22%22%2C%22pageNum%22%3A%2211%22%2C%22requestId%22%3A%22e63cdc1f7d86113e02a5c0762d22acc8%22%2C%22jobType%22%3A%220%22%7D","coId":"2329658"},{"property":"{\"isInitiative\":\"是\",\"pageCode\":\"sou|sou|soulb\",\"shortPageCode\":\"sou|sou|soulb\",\"searchType\":\"手动搜索职位\",\"jobRank\":\"219\",\"policyId\":\"{\\\"layer_rank_v23\\\":\\\"2099_2\\\"}\",\"keyword\":\"\",\"pageNum\":\"11\",\"requestId\":\"e63cdc1f7d86113e02a5c0762d22acc8\",\"jobType\":\"0\"}","jobId":"154222785","jobType":"0","jobName":"人力资源服务运营专员 (Up to Manager level)","jobTags":["5年及以上","本科","员工生命周期","数据支持","Workday","五险一金","补充医疗保险","补充公积金","年终奖金","弹性工作","定期体检","专业培训"],"jobNumString":"","workAreaCode":"021000","jobAreaCode":"020000","jobAreaString":"上海·浦东新区","hrefAreaPinYin":"shanghai-pdxq","jobAreaLevelDetail":{"provinceCode":"020000","provinceString":"上海","cityCode":"020000","cityString":"上海","districtString":"浦东新区","landMarkString":""},"provideSalaryString":"1.5-2.3万","issueDateString":"2024-04-07 14:22:43","confirmDateString":"2024-04-07 14:22:42","workYear":"6","workYearString":"5年及以上","degreeString":"本科","industryType1":"42","industryType2":"","industryType1Str":"银行","industryType2Str":"","funcType1Code":"0604","funcType2Code":"","major1Str":"","major2Str":"","encCoId":"B2ABZwJlU2QEYwxpVDk","companyName":"华侨银行","fullCompanyName":"华侨银行有限公司","companyLogo":"https://img01.51jobcdn.com/fansImg/CompLogo/2/1250/1249268/468785402028999319471_300.png?1701326609140","companyTypeString":"外资（非欧美）","companySizeString":"1000-5000人","companySizeCode":"5","companyIndustryType1Str":"银行","hrUid":"2636954","hrName":"周女士","smallHrLogoUrl":"http://img01.51jobcdn.com/imehire/userportrait/default/li_portrait_female_003_small.png","hrPosition":"人事招聘","hrMedalTitle":"","hrMedalLevel":"","showHrMedalTitle":true,"hrIsOnline":false,"isOnline":false,"hrLabels":["简历处理快"],"updateDateTime":"2024-04-30 17:57:29","lon":"121.546494","lat":"31.230973","isCommunicate":false,"isFromXyx":false,"isIntern":false,"isModelEmployer":true,"isQuickFeedback":true,"isPromotion":false,"isApply":false,"isExpire":false,"jobHref":"https://jobs.51job.com/shanghai-pdxq/154222785.html?s=sou_sou_soulb&t=0_0&req=e63cdc1f7d86113e02a5c0762d22acc8","jobDescribe":"岗位职责：\n1. 维护员工数据和档案，提供相关数据报告，为员工生命周期管理提供数据支持\n2. 负责员工入职、离职、转岗等相关工作，并持续改进和优化流程，使之符合法律法规监管和内部要求，和提高员工体验度\n3. 与HR服务供应商合作，及时提供员工的加减保信息，提供员工就业证和户籍办理的相关支持\n4. 负责HR相关的数据报告，确保数据准确性和及时提交\n5. 与集团HRIS合作，及时解决系统问题，并配合维护和升级等工作\n6. 负责供应商管理相关工作\n7. 其他人力资源服务运营经理要求的任务\n\n任职要求：\n1. 大学本科或以上学历\n2. 能熟练使用MS Office软件（包括Excel，Word等）；\n 能熟练使用常用的人力资源核心系统（如Workday）；\n 了解人力资源相关法律法规和工作流程；\n 能用英语书面和口语交流\n3. 5年以上HR相关工作经验\n4. 良好有效的沟通能力和书面表达能力；\n5. 拥有团队合作精神；\n6. 工作认真、细致、有条理；\n7. 快速的执行力和同时处理多任务的能力；\n8. 有合规和风险控制意识\n\n华侨银行有限公司（“本行”）将根据本行官网所载明的隐私政策， 严格保护您的个人信息。请您理解并知悉，您向平台和/或本行提交简历的行为视为您授权同意本行为您长期职业生涯发展和保留将来入职机会之目处理您的个人信息，您有权联系本行撤回同意。","companyHref":"https://jobs.51job.com/all/coB2ABZwJlU2QEYwxpVDk.html","allowChatOnline":false,"ctmId":187250,"term":"0","termStr":"全职","landmarkId":"","landmarkString":"","retrieverName":"JobTermBasedRetriever","exrInfo02":"{\"retrieverName\":\"JobTermBasedRetriever\",\"referJobId\":\"\",\"intentions\":\"\",\"adExtendFunc\":\"\",\"adExtendCity\":\"\"}","hrInfoType":0,"isRemoteWork":false,"contactAllowed":"0","contactDay":"","contactTime":"","hasHrMobile":true,"jobTagsForOrder":["5年及以上","本科","员工生命周期","数据支持","Workday","五险一金","补充医疗保险","补充公积金","年终奖金","弹性工作","定期体检","专业培训"],"isAllowChat":true,"sesameLabelList":[{"labelName":"发债企业","labelCode":"debt_issuing_enterprise","labelDefinition":"该企业目前在证券交易所或银行间市场进行公开募集发行信用债。"},{"labelName":"港澳台投资企业","labelCode":"hmt_owned_enterprise","labelDefinition":"该企业为全部或部分由香港特别行政区、澳门特别行政区、台湾地区投资者投资，依照中国法律在中国境内经登记注册设立。"},{"labelName":"A级纳税人","labelCode":"a_taxpayer","labelDefinition":"评定年份:2022。税务部门采用年度评价指标得分和直接判级相结合的方式，依据纳税人信用历史信息、税务内部信息和外部信息等内容对纳税人进行信用评价，按照信用程度设为A、B、C、D四级，A级纳税人是税务部门评定的纳税信用级别最高的纳税人。"}],"jobWelfareCodeDataList":[],"jobSalaryMax":"23000","jobSalaryMin":"15000","jobScheme":"qiancheng://home/show_job_info?jobid=154222785&property=%7B%22isInitiative%22%3A%22%E6%98%AF%22%2C%22pageCode%22%3A%22sou%7Csou%7Csoulb%22%2C%22shortPageCode%22%3A%22sou%7Csou%7Csoulb%22%2C%22searchType%22%3A%22%E6%89%8B%E5%8A%A8%E6%90%9C%E7%B4%A2%E8%81%8C%E4%BD%8D%22%2C%22jobRank%22%3A%22219%22%2C%22policyId%22%3A%22%7B%5C%22layer_rank_v23%5C%22%3A%5C%222099_2%5C%22%7D%22%2C%22keyword%22%3A%22%22%2C%22pageNum%22%3A%2211%22%2C%22requestId%22%3A%22e63cdc1f7d86113e02a5c0762d22acc8%22%2C%22jobType%22%3A%220%22%7D","coId":"1249268"}],"totalCount":676,"requestId":"e63cdc1f7d86113e02a5c0762d22acc8","policies":"{\"layer_rank_v23\":\"2099_2\"}","totalcount":676}}}